{"version": 0.6, "generator": "Overpass API 0.7.57 93a4d346", "osm3s": {"timestamp_osm_base": "2022-01-17T16:03:03Z", "copyright": "The data included in this document is from www.openstreetmap.org. The data is made available under ODbL."}, "elements": [{"type": "node", "id": 27749204, "lat": 43.1272139, "lon": 5.9187475}, {"type": "node", "id": 27749298, "lat": 43.1273616, "lon": 5.9196149}, {"type": "node", "id": 206144795, "lat": 43.127378, "lon": 5.918433}, {"type": "node", "id": 250040585, "lat": 43.1163441, "lon": 5.9830518}, {"type": "node", "id": 293773269, "lat": 43.1276254, "lon": 5.9183391}, {"type": "node", "id": 293773270, "lat": 43.1278991, "lon": 5.9174609, "tags": {"crossing": "traffic_signals", "crossing_ref": "zebra", "highway": "crossing"}}, {"type": "node", "id": 294001548, "lat": 43.117224, "lon": 5.9820032}, {"type": "node", "id": 294001550, "lat": 43.1176158, "lon": 5.981515}, {"type": "node", "id": 342901723, "lat": 43.1267674, "lon": 5.9133289, "tags": {"source": "cadastre-dgi-fr source : Direction G\u00e9n\u00e9rale des Imp\u00f4ts - Cadastre. Mise \u00e0 jour : 2009"}}, {"type": "node", "id": 342994450, "lat": 43.1291837, "lon": 5.9024177, "tags": {"source": "cadastre-dgi-fr source : Direction G\u00e9n\u00e9rale des Imp\u00f4ts - Cadastre. Mise \u00e0 jour : 2009"}}, {"type": "node", "id": 343057608, "lat": 43.1271785, "lon": 5.9193665, "tags": {"source": "cadastre-dgi-fr source : Direction G\u00e9n\u00e9rale des Imp\u00f4ts - Cadastre. Mise \u00e0 jour : 2009"}}, {"type": "node", "id": 343057636, "lat": 43.1270811, "lon": 5.9209421, "tags": {"source": "cadastre-dgi-fr source : Direction G\u00e9n\u00e9rale des Imp\u00f4ts - Cadastre. Mise \u00e0 jour : 2009"}}, {"type": "node", "id": 343057647, "lat": 43.1268718, "lon": 5.9206455, "tags": {"source": "cadastre-dgi-fr source : Direction G\u00e9n\u00e9rale des Imp\u00f4ts - Cadastre. Mise \u00e0 jour : 2009"}}, {"type": "node", "id": 343057650, "lat": 43.1269411, "lon": 5.9210174, "tags": {"source": "cadastre-dgi-fr source : Direction G\u00e9n\u00e9rale des Imp\u00f4ts - Cadastre. Mise \u00e0 jour : 2009"}}, {"type": "node", "id": 343057675, "lat": 43.126933, "lon": 5.9212743, "tags": {"source": "cadastre-dgi-fr source : Direction G\u00e9n\u00e9rale des Imp\u00f4ts - Cadastre. Mise \u00e0 jour : 2009"}}, {"type": "node", "id": 343057678, "lat": 43.1269175, "lon": 5.9214073, "tags": {"source": "cadastre-dgi-fr source : Direction G\u00e9n\u00e9rale des Imp\u00f4ts - Cadastre. Mise \u00e0 jour : 2009"}}, {"type": "node", "id": 343057681, "lat": 43.1267881, "lon": 5.9221541, "tags": {"source": "cadastre-dgi-fr source : Direction G\u00e9n\u00e9rale des Imp\u00f4ts - Cadastre. Mise \u00e0 jour : 2009"}}, {"type": "node", "id": 343072427, "lat": 43.1269461, "lon": 5.9211765, "tags": {"crossing": "traffic_signals", "crossing_ref": "zebra", "highway": "crossing"}}, {"type": "node", "id": 343072441, "lat": 43.1289429, "lon": 5.9024909, "tags": {"crossing": "uncontrolled", "crossing_ref": "zebra", "highway": "crossing", "source": "cadastre-dgi-fr source : Direction G\u00e9n\u00e9rale des Imp\u00f4ts - Cadastre. Mise \u00e0 jour : 2009"}}, {"type": "node", "id": 343072443, "lat": 43.1290256, "lon": 5.9024297, "tags": {"crossing": "uncontrolled", "crossing_ref": "zebra", "highway": "crossing"}}, {"type": "node", "id": 343072446, "lat": 43.1290993, "lon": 5.9024172, "tags": {"source": "cadastre-dgi-fr source : Direction G\u00e9n\u00e9rale des Imp\u00f4ts - Cadastre. Mise \u00e0 jour : 2009"}}, {"type": "node", "id": 1628397837, "lat": 43.1262918, "lon": 5.9220215}, {"type": "node", "id": 1628397844, "lat": 43.1263586, "lon": 5.9218698}, {"type": "node", "id": 1628397858, "lat": 43.126436, "lon": 5.9216993}, {"type": "node", "id": 1628397871, "lat": 43.1265255, "lon": 5.921508}, {"type": "node", "id": 1628397884, "lat": 43.1265786, "lon": 5.9213832}, {"type": "node", "id": 1628397889, "lat": 43.1266242, "lon": 5.9212876}, {"type": "node", "id": 1628397896, "lat": 43.1266591, "lon": 5.9212356}, {"type": "node", "id": 1628397916, "lat": 43.1267524, "lon": 5.9127554}, {"type": "node", "id": 1628397917, "lat": 43.1267805, "lon": 5.9211632}, {"type": "node", "id": 1628397933, "lat": 43.1268752, "lon": 5.9222144}, {"type": "node", "id": 1628397936, "lat": 43.1268654, "lon": 5.9212492}, {"type": "node", "id": 1628397938, "lat": 43.1268834, "lon": 5.9224936}, {"type": "node", "id": 1628397943, "lat": 43.1268821, "lon": 5.9220295}, {"type": "node", "id": 1628397947, "lat": 43.1268744, "lon": 5.9205756}, {"type": "node", "id": 1628397949, "lat": 43.1268929, "lon": 5.9204689}, {"type": "node", "id": 1628397953, "lat": 43.1268792, "lon": 5.9207221}, {"type": "node", "id": 1628397955, "lat": 43.1269064, "lon": 5.9211131, "tags": {"crossing": "traffic_signals", "crossing_ref": "zebra", "highway": "crossing"}}, {"type": "node", "id": 1628397958, "lat": 43.1269167, "lon": 5.9209089}, {"type": "node", "id": 1628397963, "lat": 43.1269446, "lon": 5.9217099}, {"type": "node", "id": 1628397984, "lat": 43.1269707, "lon": 5.9202513, "tags": {"source": "cadastre-dgi-fr source : Direction G\u00e9n\u00e9rale des Imp\u00f4ts - Cadastre. Mise \u00e0 jour : 2009"}}, {"type": "node", "id": 1628398018, "lat": 43.1270703, "lon": 5.9199985}, {"type": "node", "id": 1628398023, "lat": 43.1271134, "lon": 5.9207739}, {"type": "node", "id": 1628398029, "lat": 43.127134, "lon": 5.9198009}, {"type": "node", "id": 1628398031, "lat": 43.1272146, "lon": 5.9202737, "tags": {"source": "cadastre-dgi-fr source : Direction G\u00e9n\u00e9rale des Imp\u00f4ts - Cadastre. Mise \u00e0 jour : 2009"}}, {"type": "node", "id": 1628398038, "lat": 43.1271587, "lon": 5.919673}, {"type": "node", "id": 1628398039, "lat": 43.1272761, "lon": 5.9200974}, {"type": "node", "id": 1628398065, "lat": 43.1272545, "lon": 5.9199245}, {"type": "node", "id": 1628398068, "lat": 43.1273077, "lon": 5.919929}, {"type": "node", "id": 1628398070, "lat": 43.1272846, "lon": 5.9196982}, {"type": "node", "id": 1628398072, "lat": 43.1272954, "lon": 5.9185862}, {"type": "node", "id": 1628398074, "lat": 43.1273142, "lon": 5.9193917}, {"type": "node", "id": 1628398076, "lat": 43.1273344, "lon": 5.9190586}, {"type": "node", "id": 1628398097, "lat": 43.1273955, "lon": 5.9194248}, {"type": "node", "id": 1628398102, "lat": 43.1274269, "lon": 5.91924}, {"type": "node", "id": 1628398104, "lat": 43.1274728, "lon": 5.9182706}, {"type": "node", "id": 1628398111, "lat": 43.1275211, "lon": 5.9188039}, {"type": "node", "id": 1628398116, "lat": 43.1277369, "lon": 5.9179302}, {"type": "node", "id": 1628543402, "lat": 43.126766, "lon": 5.9136774}, {"type": "node", "id": 1642884066, "lat": 43.1238912, "lon": 5.9364567, "tags": {"crossing": "traffic_signals", "highway": "crossing"}}, {"type": "node", "id": 1642884067, "lat": 43.123931, "lon": 5.9366933}, {"type": "node", "id": 1642884073, "lat": 43.1239131, "lon": 5.9365564}, {"type": "node", "id": 2123994614, "lat": 43.1270352, "lon": 5.9212087, "tags": {"crossing": "traffic_signals", "highway": "crossing"}}, {"type": "node", "id": 2123994624, "lat": 43.1274451, "lon": 5.9191556}, {"type": "node", "id": 2123994629, "lat": 43.1274717, "lon": 5.9190326, "tags": {"crossing": "uncontrolled", "crossing_ref": "zebra", "highway": "crossing"}}, {"type": "node", "id": 2123994632, "lat": 43.1275694, "lon": 5.9180932, "tags": {"source": "cadastre-dgi-fr source : Direction G\u00e9n\u00e9rale des Imp\u00f4ts - Cadastre. Mise \u00e0 jour : 2009"}}, {"type": "node", "id": 2123994646, "lat": 43.1276478, "lon": 5.9182386, "tags": {"crossing": "traffic_signals", "highway": "crossing"}}, {"type": "node", "id": 2345282577, "lat": 43.1267633, "lon": 5.9223258, "tags": {"source": "cadastre-dgi-fr source : Direction G\u00e9n\u00e9rale des Imp\u00f4ts - Cadastre. Mise \u00e0 jour : 2009"}}, {"type": "node", "id": 2345285799, "lat": 43.1266469, "lon": 5.9113449, "tags": {"highway": "motorway_junction", "name": "Toulon le Port", "ref": "16"}}, {"type": "node", "id": 2349727212, "lat": 43.1267967, "lon": 5.9228845}, {"type": "node", "id": 3472022072, "lat": 43.1267759, "lon": 5.9227025}, {"type": "node", "id": 3472022074, "lat": 43.1268855, "lon": 5.9224185}, {"type": "node", "id": 3472022075, "lat": 43.1269469, "lon": 5.9210924}, {"type": "node", "id": 4030926018, "lat": 43.1262382, "lon": 5.9221371}, {"type": "node", "id": 5062796419, "lat": 43.1267229, "lon": 5.9123115}, {"type": "node", "id": 5062796521, "lat": 43.1266831, "lon": 5.9119124}, {"type": "node", "id": 5996217318, "lat": 43.1274628, "lon": 5.9182877, "tags": {"crossing": "zebra", "highway": "crossing"}}, {"type": "node", "id": 6327583289, "lat": 43.1237695, "lon": 5.9362817}, {"type": "node", "id": 7002185278, "lat": 43.1267199, "lon": 5.9211864}, {"type": "node", "id": 7344010945, "lat": 43.1268976, "lon": 5.9211166, "tags": {"highway": "traffic_signals", "traffic_signals": "signal", "traffic_signals:direction": "forward"}}, {"type": "node", "id": 7471758073, "lat": 43.1278274, "lon": 5.9177235, "tags": {"direction": "forward", "highway": "give_way"}}, {"type": "node", "id": 7471758079, "lat": 43.1267626, "lon": 5.9224746}, {"type": "node", "id": 9363606136, "lat": 43.1270473, "lon": 5.9209992}, {"type": "node", "id": 9363606137, "lat": 43.1270086, "lon": 5.9210475}, {"type": "node", "id": 9363751184, "lat": 43.1268936, "lon": 5.9213157, "tags": {"highway": "traffic_signals", "traffic_signals": "signal", "traffic_signals:direction": "forward"}}, {"type": "node", "id": 9363751185, "lat": 43.1268305, "lon": 5.9212037}, {"type": "node", "id": 9364102605, "lat": 43.1289862, "lon": 5.9024504}, {"type": "node", "id": 9366203447, "lat": 43.1238402, "lon": 5.9363589}, {"type": "node", "id": 9383697653, "lat": 43.1275739, "lon": 5.9185684}, {"type": "way", "id": 26800507, "nodes": [250040585, 294001548], "tags": {"highway": "primary_link", "name": "Avenue Jules Charleux", "oneway": "yes", "ref": "D 559"}}, {"type": "way", "id": 26800508, "nodes": [294001548, 294001550], "tags": {"bridge": "yes", "highway": "primary_link", "layer": "1", "name": "Avenue Joseph Gasquet", "oneway": "yes"}}, {"type": "way", "id": 30841921, "nodes": [2123994632, 1628398104, 5996217318, 206144795], "tags": {"cycleway:right": "no", "highway": "primary_link", "old_ref": "N 8", "oneway": "yes", "ref": "D N8", "source": "cadastre-dgi-fr source : Direction G\u00e9n\u00e9rale des Imp\u00f4ts - Cadastre. Mise \u00e0 jour : 2009"}}, {"type": "way", "id": 30841933, "nodes": [1628398031, 1628398039, 1628398068, 27749298, 1628398097, 1628398102, 2123994624, 2123994629, 1628398111, 9383697653, 293773269], "tags": {"highway": "primary_link", "old_ref": "N 8", "oneway": "yes", "ref": "N 8", "source": "cadastre-dgi-fr source : Direction G\u00e9n\u00e9rale des Imp\u00f4ts - Cadastre. Mise \u00e0 jour : 2009", "surface": "asphalt"}}, {"type": "way", "id": 30842403, "nodes": [343072441, 9364102605, 343072443, 343072446, 342994450], "tags": {"highway": "primary_link", "name": "Quai Marmora", "oneway": "yes", "source": "cadastre-dgi-fr source : Direction G\u00e9n\u00e9rale des Imp\u00f4ts - Cadastre. Mise \u00e0 jour : 2009", "surface": "asphalt"}}, {"type": "way", "id": 30878507, "nodes": [343057608, 1628398038, 1628398029, 1628398018, 1628397984, 1628397949, 1628397947, 343057647, 1628397953, 1628397958, 343057650, 3472022075], "tags": {"cycleway": "no", "highway": "primary_link", "name": "Carrefour Villevieille", "old_ref": "N 8", "oneway": "yes", "ref": "N 8", "surface": "asphalt"}}, {"type": "way", "id": 39691873, "nodes": [2349727212, 1628397938], "tags": {"highway": "primary_link", "old_ref": "N 8", "oneway": "yes", "ref": "D N8", "surface": "asphalt"}}, {"type": "way", "id": 149904013, "nodes": [1628397917, 9363751185, 1628397936, 9363751184, 343057678], "tags": {"cycleway:right": "no", "highway": "primary_link", "lane_markings": "no", "name": "Rue Robert Guillemard", "oneway": "yes", "surface": "asphalt"}}, {"type": "way", "id": 151468221, "nodes": [6327583289, 9366203447, 1642884066, 1642884073, 1642884067], "tags": {"highway": "primary_link", "oneway": "yes", "source": "cadastre-dgi-fr source : Direction G\u00e9n\u00e9rale des Imp\u00f4ts - Cadastre. Mise \u00e0 jour : 2012"}}, {"type": "way", "id": 300116418, "nodes": [2345282577, 7471758079, 3472022072, 2349727212], "tags": {"highway": "primary_link", "old_ref": "N 8", "oneway": "yes", "ref": "D N8", "surface": "asphalt"}}, {"type": "way", "id": 300116425, "nodes": [3472022074, 1628397933, 1628397943, 1628397963, 2123994614, 343057636], "tags": {"highway": "primary_link", "name": "Carrefour Villevieille", "old_ref": "N 8", "oneway": "yes", "ref": "N 8", "surface": "asphalt"}}, {"type": "way", "id": 303163129, "nodes": [343057636, 1628398023, 1628398031, 1628398065, 1628398070, 1628398074, 1628398076, 206144795], "tags": {"highway": "primary_link", "old_ref": "N 8", "oneway": "yes", "ref": "N 8", "surface": "asphalt"}}, {"type": "way", "id": 413032283, "nodes": [2345285799, 5062796521, 5062796419, 1628397916, 342901723, 1628543402], "tags": {"highway": "primary_link", "lanes": "2", "maxspeed": "50", "oneway": "yes", "source": "cadastre-dgi-fr source : Direction G\u00e9n\u00e9rale des Imp\u00f4ts - Cadastre. Mise \u00e0 jour : 2009", "surface": "asphalt", "toll": "no"}}, {"type": "way", "id": 680501772, "nodes": [206144795, 1628398072, 27749204], "tags": {"cycleway:right": "no", "highway": "primary_link", "old_ref": "N 8", "oneway": "yes", "ref": "D N8", "source": "cadastre-dgi-fr source : Direction G\u00e9n\u00e9rale des Imp\u00f4ts - Cadastre. Mise \u00e0 jour : 2009", "surface": "asphalt"}}, {"type": "way", "id": 796568894, "nodes": [4030926018, 1628397837, 1628397844, 1628397858, 1628397871, 1628397884, 1628397889, 1628397896, 7002185278, 1628397917, 7344010945, 1628397955, 3472022075], "tags": {"highway": "primary_link", "lanes": "2", "name": "Rue Robert Guillemard", "oneway": "yes", "surface": "asphalt"}}, {"type": "way", "id": 961292956, "nodes": [1628397938, 3472022074], "tags": {"highway": "primary_link", "old_ref": "N 8", "oneway": "yes", "ref": "N 8", "surface": "asphalt"}}, {"type": "way", "id": 1013323528, "nodes": [293773269, 2123994646, 1628398116, 7471758073, 293773270], "tags": {"highway": "primary_link", "old_ref": "N 8", "oneway": "yes", "ref": "N 8", "source": "cadastre-dgi-fr source : Direction G\u00e9n\u00e9rale des Imp\u00f4ts - Cadastre. Mise \u00e0 jour : 2009", "surface": "asphalt"}}, {"type": "way", "id": 1017349483, "nodes": [3472022075, 343072427, 343057675, 343057678, 343057681, 2345282577], "tags": {"cycleway": "no", "highway": "primary_link", "name": "Carrefour Villevieille", "old_ref": "N 8", "oneway": "yes", "ref": "N 8", "surface": "asphalt"}}, {"type": "way", "id": 1017349484, "nodes": [3472022075, 9363606137, 9363606136, 343057636], "tags": {"highway": "primary_link", "lanes": "2", "name": "Carrefour Villevieille", "oneway": "yes", "surface": "asphalt"}}]}