{"version": 0.6, "generator": "Overpass API 0.7.57 93a4d346", "osm3s": {"timestamp_osm_base": "2022-01-17T15:53:54Z", "copyright": "The data included in this document is from www.openstreetmap.org. The data is made available under ODbL."}, "elements": [{"type": "node", "id": 21459451, "lat": 44.8295381, "lon": -0.554752}, {"type": "node", "id": 35232795, "lat": 44.8316768, "lon": -0.557034}, {"type": "node", "id": 35232797, "lat": 44.8317018, "lon": -0.5575136}, {"type": "node", "id": 35232802, "lat": 44.8318756, "lon": -0.5572771}, {"type": "node", "id": 35232813, "lat": 44.8307744, "lon": -0.5557262}, {"type": "node", "id": 35232824, "lat": 44.8305943, "lon": -0.5564466}, {"type": "node", "id": 35232825, "lat": 44.8307507, "lon": -0.5568262}, {"type": "node", "id": 35232826, "lat": 44.8309108, "lon": -0.5569368}, {"type": "node", "id": 35232827, "lat": 44.8311022, "lon": -0.556963}, {"type": "node", "id": 35232829, "lat": 44.8315259, "lon": -0.5569602}, {"type": "node", "id": 35232830, "lat": 44.8307233, "lon": -0.556877}, {"type": "node", "id": 35232833, "lat": 44.831434, "lon": -0.5572842}, {"type": "node", "id": 35232840, "lat": 44.8296916, "lon": -0.5546593}, {"type": "node", "id": 35232841, "lat": 44.8297739, "lon": -0.5546496}, {"type": "node", "id": 35232842, "lat": 44.8299559, "lon": -0.5547938}, {"type": "node", "id": 35232843, "lat": 44.8300885, "lon": -0.5550454}, {"type": "node", "id": 35232844, "lat": 44.8302405, "lon": -0.5553476}, {"type": "node", "id": 35232845, "lat": 44.8303754, "lon": -0.5555435}, {"type": "node", "id": 35232846, "lat": 44.8307081, "lon": -0.555599}, {"type": "node", "id": 35234319, "lat": 44.8449257, "lon": -0.5394372}, {"type": "node", "id": 35234327, "lat": 44.8480596, "lon": -0.537498}, {"type": "node", "id": 35234366, "lat": 44.844973, "lon": -0.539562}, {"type": "node", "id": 35234387, "lat": 44.8376498, "lon": -0.5485698}, {"type": "node", "id": 35234833, "lat": 44.8340059, "lon": -0.5507646}, {"type": "node", "id": 35234867, "lat": 44.8374872, "lon": -0.5501858}, {"type": "node", "id": 35234871, "lat": 44.8372684, "lon": -0.5507676}, {"type": "node", "id": 35234874, "lat": 44.8352553, "lon": -0.5531979}, {"type": "node", "id": 35237795, "lat": 44.8464324, "lon": -0.5360963}, {"type": "node", "id": 35237812, "lat": 44.8464853, "lon": -0.5389591}, {"type": "node", "id": 35237815, "lat": 44.8465071, "lon": -0.5398126}, {"type": "node", "id": 35237868, "lat": 44.8464218, "lon": -0.5397283}, {"type": "node", "id": 35237872, "lat": 44.8464178, "lon": -0.5388376}, {"type": "node", "id": 35237885, "lat": 44.8465148, "lon": -0.5375131}, {"type": "node", "id": 35237917, "lat": 44.8463817, "lon": -0.5392591}, {"type": "node", "id": 35237920, "lat": 44.8463668, "lon": -0.5390713}, {"type": "node", "id": 35237925, "lat": 44.8463112, "lon": -0.5389422, "tags": {"crossing": "uncontrolled", "highway": "crossing"}}, {"type": "node", "id": 35237929, "lat": 44.8461682, "lon": -0.538816}, {"type": "node", "id": 35237933, "lat": 44.8460477, "lon": -0.5388068}, {"type": "node", "id": 35237936, "lat": 44.8458212, "lon": -0.5389008}, {"type": "node", "id": 35237943, "lat": 44.8454113, "lon": -0.5387961}, {"type": "node", "id": 35237945, "lat": 44.8456762, "lon": -0.5384822}, {"type": "node", "id": 35237949, "lat": 44.8459906, "lon": -0.53815}, {"type": "node", "id": 35237952, "lat": 44.8461404, "lon": -0.537982}, {"type": "node", "id": 35237955, "lat": 44.8464305, "lon": -0.5376559, "tags": {"crossing": "traffic_signals", "highway": "crossing"}}, {"type": "node", "id": 35237958, "lat": 44.8466005, "lon": -0.5379233}, {"type": "node", "id": 35237960, "lat": 44.8465572, "lon": -0.5383701}, {"type": "node", "id": 35237964, "lat": 44.846569, "lon": -0.5387043}, {"type": "node", "id": 35237968, "lat": 44.8466728, "lon": -0.5389415}, {"type": "node", "id": 35237971, "lat": 44.846829, "lon": -0.5390493}, {"type": "node", "id": 35237973, "lat": 44.8470029, "lon": -0.5390255}, {"type": "node", "id": 35237977, "lat": 44.8470975, "lon": -0.5389583}, {"type": "node", "id": 35237980, "lat": 44.8471529, "lon": -0.5388792}, {"type": "node", "id": 35237982, "lat": 44.8472292, "lon": -0.5385888}, {"type": "node", "id": 35237985, "lat": 44.8472179, "lon": -0.5384779}, {"type": "node", "id": 35237988, "lat": 44.8471734, "lon": -0.5383189}, {"type": "node", "id": 35237991, "lat": 44.847073, "lon": -0.5381879}, {"type": "node", "id": 35237994, "lat": 44.8469588, "lon": -0.5381192}, {"type": "node", "id": 35237997, "lat": 44.8468949, "lon": -0.5381113}, {"type": "node", "id": 35238000, "lat": 44.8468253, "lon": -0.53813}, {"type": "node", "id": 35238003, "lat": 44.8467514, "lon": -0.5381713}, {"type": "node", "id": 35238005, "lat": 44.8478895, "lon": -0.5376376}, {"type": "node", "id": 35238009, "lat": 44.8474101, "lon": -0.5378234}, {"type": "node", "id": 35238012, "lat": 44.8473365, "lon": -0.537865}, {"type": "node", "id": 35238014, "lat": 44.8472874, "lon": -0.5379431}, {"type": "node", "id": 35238017, "lat": 44.8472566, "lon": -0.5380123}, {"type": "node", "id": 35238019, "lat": 44.8472377, "lon": -0.5381052}, {"type": "node", "id": 35238023, "lat": 44.8472468, "lon": -0.5383434}, {"type": "node", "id": 35238026, "lat": 44.8472713, "lon": -0.5384719}, {"type": "node", "id": 35238029, "lat": 44.847281, "lon": -0.5385857, "tags": {"created_by": "JOSM"}}, {"type": "node", "id": 35238032, "lat": 44.8472692, "lon": -0.5387141}, {"type": "node", "id": 35238034, "lat": 44.8471879, "lon": -0.5389346}, {"type": "node", "id": 35238036, "lat": 44.8471255, "lon": -0.5390097}, {"type": "node", "id": 35238040, "lat": 44.8469987, "lon": -0.5391247}, {"type": "node", "id": 35238043, "lat": 44.8469678, "lon": -0.5391398}, {"type": "node", "id": 35238045, "lat": 44.8468981, "lon": -0.5392008}, {"type": "node", "id": 35238048, "lat": 44.8466852, "lon": -0.5393738}, {"type": "node", "id": 35238050, "lat": 44.8465375, "lon": -0.5396503}, {"type": "node", "id": 35238054, "lat": 44.8468291, "lon": -0.5391571}, {"type": "node", "id": 35238058, "lat": 44.8465647, "lon": -0.5390362, "tags": {"highway": "traffic_signals", "traffic_signals": "signal", "traffic_signals:direction": "forward"}}, {"type": "node", "id": 35238061, "lat": 44.8465995, "lon": -0.5365376}, {"type": "node", "id": 35238066, "lat": 44.8466879, "lon": -0.5371476}, {"type": "node", "id": 35238068, "lat": 44.8468611, "lon": -0.5375654}, {"type": "node", "id": 35238071, "lat": 44.8469268, "lon": -0.5376263}, {"type": "node", "id": 35238075, "lat": 44.8470063, "lon": -0.5376684}, {"type": "node", "id": 35238077, "lat": 44.8472499, "lon": -0.5376611}, {"type": "node", "id": 253946791, "lat": 44.8239376, "lon": -0.5442459}, {"type": "node", "id": 253946793, "lat": 44.8241643, "lon": -0.544506}, {"type": "node", "id": 253946802, "lat": 44.8240605, "lon": -0.5441506}, {"type": "node", "id": 253946803, "lat": 44.8241288, "lon": -0.5438751}, {"type": "node", "id": 253946804, "lat": 44.8239278, "lon": -0.5434392}, {"type": "node", "id": 257740410, "lat": 44.8105872, "lon": -0.5329559}, {"type": "node", "id": 260354778, "lat": 44.8436802, "lon": -0.5076178}, {"type": "node", "id": 260354823, "lat": 44.8442248, "lon": -0.5152924}, {"type": "node", "id": 260953219, "lat": 44.844351, "lon": -0.5152771}, {"type": "node", "id": 260953262, "lat": 44.8442491, "lon": -0.5110033}, {"type": "node", "id": 260953379, "lat": 44.843886, "lon": -0.5109029}, {"type": "node", "id": 260953380, "lat": 44.8442119, "lon": -0.5108175}, {"type": "node", "id": 260953381, "lat": 44.8439214, "lon": -0.511094}, {"type": "node", "id": 260954019, "lat": 44.8436036, "lon": -0.507631}, {"type": "node", "id": 260954203, "lat": 44.8439504, "lon": -0.5093094}, {"type": "node", "id": 272268764, "lat": 44.8145691, "lon": -0.5714054}, {"type": "node", "id": 279709943, "lat": 44.8296252, "lon": -0.5546832}, {"type": "node", "id": 280478284, "lat": 44.8111255, "lon": -0.5334501}, {"type": "node", "id": 280518936, "lat": 44.8642402, "lon": -0.5205378}, {"type": "node", "id": 280518943, "lat": 44.8643107, "lon": -0.5198911}, {"type": "node", "id": 280519104, "lat": 44.8648021, "lon": -0.5174197}, {"type": "node", "id": 288123369, "lat": 44.8358727, "lon": -0.5502007, "tags": {"highway": "traffic_signals", "traffic_signals": "signal", "traffic_signals:direction": "forward"}}, {"type": "node", "id": 288513883, "lat": 44.8369171, "lon": -0.5512679}, {"type": "node", "id": 290613159, "lat": 44.864062, "lon": -0.5207327}, {"type": "node", "id": 290613161, "lat": 44.863782, "lon": -0.5240672}, {"type": "node", "id": 290613211, "lat": 44.8639057, "lon": -0.5211021}, {"type": "node", "id": 290613280, "lat": 44.8646745, "lon": -0.517658}, {"type": "node", "id": 411082311, "lat": 44.8462307, "lon": -0.5384929}, {"type": "node", "id": 417092258, "lat": 44.8147521, "lon": -0.5726195, "tags": {"highway": "motorway_junction", "name": "Barri\u00e8re de Toulouse"}}, {"type": "node", "id": 476668275, "lat": 44.8642726, "lon": -0.5197657}, {"type": "node", "id": 476668563, "lat": 44.8641368, "lon": -0.5197445}, {"type": "node", "id": 570287339, "lat": 44.8636619, "lon": -0.5236174}, {"type": "node", "id": 570287345, "lat": 44.8638109, "lon": -0.5216996}, {"type": "node", "id": 570287347, "lat": 44.863698, "lon": -0.5216522}, {"type": "node", "id": 570287351, "lat": 44.8637954, "lon": -0.5210432}, {"type": "node", "id": 570287353, "lat": 44.863976, "lon": -0.5201674}, {"type": "node", "id": 570287359, "lat": 44.8640823, "lon": -0.5198518}, {"type": "node", "id": 915926782, "lat": 44.8361025, "lon": -0.5522078}, {"type": "node", "id": 1037549996, "lat": 44.8374239, "lon": -0.5503884}, {"type": "node", "id": 1037550007, "lat": 44.8375562, "lon": -0.5497257}, {"type": "node", "id": 1222773153, "lat": 44.8244756, "lon": -0.5443641}, {"type": "node", "id": 1222773154, "lat": 44.82439, "lon": -0.5443376}, {"type": "node", "id": 1222773156, "lat": 44.8241278, "lon": -0.5439762}, {"type": "node", "id": 1222773157, "lat": 44.8242542, "lon": -0.5443684}, {"type": "node", "id": 1222773161, "lat": 44.8241927, "lon": -0.5444267, "tags": {"highway": "give_way"}}, {"type": "node", "id": 1222773167, "lat": 44.8246917, "lon": -0.5445409}, {"type": "node", "id": 1471045162, "lat": 44.8437492, "lon": -0.5093433}, {"type": "node", "id": 1471045219, "lat": 44.8441484, "lon": -0.5107223, "tags": {"highway": "crossing"}}, {"type": "node", "id": 1471045227, "lat": 44.84424, "lon": -0.5129719}, {"type": "node", "id": 1471045240, "lat": 44.8443676, "lon": -0.5140086}, {"type": "node", "id": 1471045243, "lat": 44.8443481, "lon": -0.5123113}, {"type": "node", "id": 1471045251, "lat": 44.8444775, "lon": -0.5132896}, {"type": "node", "id": 1471045256, "lat": 44.8445244, "lon": -0.5136848}, {"type": "node", "id": 1471045258, "lat": 44.8445456, "lon": -0.5139952}, {"type": "node", "id": 1472201150, "lat": 44.8298573, "lon": -0.55469}, {"type": "node", "id": 1581019343, "lat": 44.8364208, "lon": -0.55185}, {"type": "node", "id": 1581062441, "lat": 44.8304775, "lon": -0.5556117}, {"type": "node", "id": 1581062466, "lat": 44.8305905, "lon": -0.5556325}, {"type": "node", "id": 1581075033, "lat": 44.8308322, "lon": -0.5568999}, {"type": "node", "id": 1581075052, "lat": 44.8306601, "lon": -0.5567643}, {"type": "node", "id": 1581075072, "lat": 44.8306704, "lon": -0.5558719}, {"type": "node", "id": 1581075081, "lat": 44.8306493, "lon": -0.5566305}, {"type": "node", "id": 1581075083, "lat": 44.8305933, "lon": -0.5562006}, {"type": "node", "id": 1581075092, "lat": 44.8309973, "lon": -0.5556472}, {"type": "node", "id": 1581075094, "lat": 44.8315967, "lon": -0.5573868, "tags": {"highway": "traffic_signals", "traffic_signals": "signal", "traffic_signals:direction": "forward"}}, {"type": "node", "id": 1673087221, "lat": 44.8306438, "lon": -0.5562078}, {"type": "node", "id": 1673087229, "lat": 44.8311115, "lon": -0.5567358}, {"type": "node", "id": 1673087232, "lat": 44.8311646, "lon": -0.556679}, {"type": "node", "id": 1673087233, "lat": 44.8309877, "lon": -0.5567889}, {"type": "node", "id": 1673087234, "lat": 44.8312121, "lon": -0.5566092}, {"type": "node", "id": 1673087236, "lat": 44.8306681, "lon": -0.5560515}, {"type": "node", "id": 1673087241, "lat": 44.8309116, "lon": -0.5567863}, {"type": "node", "id": 1673087252, "lat": 44.8310528, "lon": -0.5567703}, {"type": "node", "id": 1673087258, "lat": 44.8312611, "lon": -0.5564246}, {"type": "node", "id": 1673087262, "lat": 44.8308435, "lon": -0.5567631}, {"type": "node", "id": 1673087265, "lat": 44.8312464, "lon": -0.5565127}, {"type": "node", "id": 1673087267, "lat": 44.8312162, "lon": -0.5561567}, {"type": "node", "id": 1673087272, "lat": 44.8307841, "lon": -0.5567219}, {"type": "node", "id": 1673087274, "lat": 44.8306476, "lon": -0.5564144}, {"type": "node", "id": 1673087275, "lat": 44.8306874, "lon": -0.5565776}, {"type": "node", "id": 1673087276, "lat": 44.8307255, "lon": -0.5566498}, {"type": "node", "id": 1673087277, "lat": 44.8312468, "lon": -0.5562547}, {"type": "node", "id": 1673093169, "lat": 44.8340902, "lon": -0.550665, "tags": {"highway": "crossing"}}, {"type": "node", "id": 1673093256, "lat": 44.8342009, "lon": -0.5504654}, {"type": "node", "id": 1673093260, "lat": 44.8342734, "lon": -0.5503297}, {"type": "node", "id": 1673093267, "lat": 44.834358, "lon": -0.5502176}, {"type": "node", "id": 1673093317, "lat": 44.8341529, "lon": -0.5505527}, {"type": "node", "id": 1673097815, "lat": 44.8339435, "lon": -0.5506536}, {"type": "node", "id": 1673097827, "lat": 44.8356877, "lon": -0.5501682}, {"type": "node", "id": 1673097830, "lat": 44.8349381, "lon": -0.5499695}, {"type": "node", "id": 1673104946, "lat": 44.8353008, "lon": -0.5531543, "tags": {"highway": "crossing"}}, {"type": "node", "id": 1935345768, "lat": 44.8146055, "lon": -0.5718167}, {"type": "node", "id": 1935345785, "lat": 44.8146899, "lon": -0.5726205}, {"type": "node", "id": 1935345787, "lat": 44.8146956, "lon": -0.5725258, "tags": {"crossing": "traffic_signals", "crossing_ref": "zebra", "highway": "crossing"}}, {"type": "node", "id": 1973883978, "lat": 44.8146847, "lon": -0.5726345}, {"type": "node", "id": 1973883981, "lat": 44.8148102, "lon": -0.5726092}, {"type": "node", "id": 1978021383, "lat": 44.8240037, "lon": -0.5442082}, {"type": "node", "id": 1978021386, "lat": 44.8240936, "lon": -0.5437554}, {"type": "node", "id": 1978021388, "lat": 44.8241025, "lon": -0.5440688}, {"type": "node", "id": 1978021394, "lat": 44.8240946, "lon": -0.5443003}, {"type": "node", "id": 1978021413, "lat": 44.8243219, "lon": -0.5443433}, {"type": "node", "id": 1979289525, "lat": 44.826626, "lon": -0.5475173, "tags": {"highway": "traffic_signals", "traffic_signals": "signal"}}, {"type": "node", "id": 1979396449, "lat": 44.8295464, "lon": -0.554741}, {"type": "node", "id": 1981045036, "lat": 44.8304206, "lon": -0.5555795}, {"type": "node", "id": 1981045038, "lat": 44.8305187, "lon": -0.5544844}, {"type": "node", "id": 1981045040, "lat": 44.8305297, "lon": -0.5556271}, {"type": "node", "id": 1981045046, "lat": 44.8305893, "lon": -0.5563127}, {"type": "node", "id": 1981045053, "lat": 44.8306041, "lon": -0.5561133}, {"type": "node", "id": 1981045056, "lat": 44.8306208, "lon": -0.5566474}, {"type": "node", "id": 1981045059, "lat": 44.8306212, "lon": -0.5560295}, {"type": "node", "id": 1981045063, "lat": 44.8306402, "lon": -0.5563152}, {"type": "node", "id": 1981045066, "lat": 44.8306433, "lon": -0.5559501}, {"type": "node", "id": 1981045084, "lat": 44.8306543, "lon": -0.5561228}, {"type": "node", "id": 1981045086, "lat": 44.830661, "lon": -0.5564948}, {"type": "node", "id": 1981045090, "lat": 44.830688, "lon": -0.5559752}, {"type": "node", "id": 1981045091, "lat": 44.8306909, "lon": -0.5567262}, {"type": "node", "id": 1981045101, "lat": 44.8308016, "lon": -0.5569784}, {"type": "node", "id": 1981045108, "lat": 44.8308758, "lon": -0.5570412}, {"type": "node", "id": 1981045135, "lat": 44.8309854, "lon": -0.5569612}, {"type": "node", "id": 1981045154, "lat": 44.8312617, "lon": -0.5563441}, {"type": "node", "id": 1981045194, "lat": 44.8314191, "lon": -0.5569411}, {"type": "node", "id": 1981045211, "lat": 44.8315064, "lon": -0.5573198}, {"type": "node", "id": 1981045234, "lat": 44.8316162, "lon": -0.5570015, "tags": {"highway": "traffic_signals", "traffic_signals": "signal", "traffic_signals:direction": "forward"}}, {"type": "node", "id": 1981045235, "lat": 44.8316495, "lon": -0.5574359}, {"type": "node", "id": 1981045256, "lat": 44.8317392, "lon": -0.5570818}, {"type": "node", "id": 1981045282, "lat": 44.8317981, "lon": -0.5571502}, {"type": "node", "id": 2493896459, "lat": 44.8475818, "lon": -0.5377671}, {"type": "node", "id": 2493896464, "lat": 44.8478895, "lon": -0.5375031}, {"type": "node", "id": 2493896465, "lat": 44.8470945, "lon": -0.5376756}, {"type": "node", "id": 2493896468, "lat": 44.847022, "lon": -0.5381466}, {"type": "node", "id": 2493896469, "lat": 44.8471185, "lon": -0.5382391}, {"type": "node", "id": 2493896470, "lat": 44.8472015, "lon": -0.5384024}, {"type": "node", "id": 2493896471, "lat": 44.847218, "lon": -0.5387037}, {"type": "node", "id": 2493896472, "lat": 44.8472377, "lon": -0.5388318}, {"type": "node", "id": 2493896473, "lat": 44.8472377, "lon": -0.5382297}, {"type": "node", "id": 2493896474, "lat": 44.8468153, "lon": -0.5392576}, {"type": "node", "id": 2493896475, "lat": 44.8465871, "lon": -0.5395271, "tags": {"highway": "traffic_signals", "traffic_signals": "signal", "traffic_signals:direction": "forward"}}, {"type": "node", "id": 2493896476, "lat": 44.84693, "lon": -0.5390532}, {"type": "node", "id": 2493896477, "lat": 44.8467307, "lon": -0.5391306}, {"type": "node", "id": 2493896478, "lat": 44.8467421, "lon": -0.5390107}, {"type": "node", "id": 2493896479, "lat": 44.8466146, "lon": -0.5388506}, {"type": "node", "id": 2493896480, "lat": 44.8465487, "lon": -0.5385421}, {"type": "node", "id": 2493901265, "lat": 44.8468303, "lon": -0.5375285, "tags": {"direction": "forward", "highway": "give_way"}}, {"type": "node", "id": 2493901267, "lat": 44.8467165, "lon": -0.5372978}, {"type": "node", "id": 2493901269, "lat": 44.8465687, "lon": -0.5364018}, {"type": "node", "id": 2493901289, "lat": 44.8464702, "lon": -0.5376051}, {"type": "node", "id": 2495308361, "lat": 44.8463403, "lon": -0.5389848}, {"type": "node", "id": 2495308363, "lat": 44.8462305, "lon": -0.5388562}, {"type": "node", "id": 2495308365, "lat": 44.8461053, "lon": -0.538801}, {"type": "node", "id": 2495308367, "lat": 44.8459782, "lon": -0.5388211}, {"type": "node", "id": 2495308369, "lat": 44.846373, "lon": -0.5391344}, {"type": "node", "id": 2495308371, "lat": 44.8463579, "lon": -0.5390321}, {"type": "node", "id": 2495308373, "lat": 44.8464471, "lon": -0.5389031}, {"type": "node", "id": 2496121509, "lat": 44.8443467, "lon": -0.5136956}, {"type": "node", "id": 2496121514, "lat": 44.8443027, "lon": -0.5133856}, {"type": "node", "id": 2496121518, "lat": 44.844417, "lon": -0.51279}, {"type": "node", "id": 2496121531, "lat": 44.8441449, "lon": -0.5123418}, {"type": "node", "id": 2496121535, "lat": 44.8442127, "lon": -0.5111262, "tags": {"highway": "crossing"}}, {"type": "node", "id": 2496121541, "lat": 44.8439776, "lon": -0.5111918, "tags": {"highway": "crossing"}}, {"type": "node", "id": 2496121548, "lat": 44.8442183, "lon": -0.5113189}, {"type": "node", "id": 2496121553, "lat": 44.8439059, "lon": -0.5107941, "tags": {"highway": "crossing"}}, {"type": "node", "id": 2496127697, "lat": 44.843949, "lon": -0.5111261}, {"type": "node", "id": 2496127698, "lat": 44.8439617, "lon": -0.5111458}, {"type": "node", "id": 2496127699, "lat": 44.844229, "lon": -0.5110533}, {"type": "node", "id": 2496127700, "lat": 44.8442168, "lon": -0.5110857}, {"type": "node", "id": 2496127701, "lat": 44.8441791, "lon": -0.5107861}, {"type": "node", "id": 2496127702, "lat": 44.8441629, "lon": -0.5107602}, {"type": "node", "id": 2496127703, "lat": 44.8439001, "lon": -0.5108542}, {"type": "node", "id": 2496127704, "lat": 44.8439026, "lon": -0.5108339}, {"type": "node", "id": 2496135807, "lat": 44.8438675, "lon": -0.5103111}, {"type": "node", "id": 2496135808, "lat": 44.8440777, "lon": -0.5102631}, {"type": "node", "id": 2496135809, "lat": 44.8436486, "lon": -0.508431}, {"type": "node", "id": 2496135810, "lat": 44.8438215, "lon": -0.5083872}, {"type": "node", "id": 2499901482, "lat": 44.8637159, "lon": -0.5229042}, {"type": "node", "id": 2499901494, "lat": 44.8637143, "lon": -0.5231607}, {"type": "node", "id": 2499901497, "lat": 44.8637414, "lon": -0.5236125}, {"type": "node", "id": 2499901499, "lat": 44.8636176, "lon": -0.522907}, {"type": "node", "id": 2499901504, "lat": 44.8636199, "lon": -0.523169}, {"type": "node", "id": 2499901514, "lat": 44.8636455, "lon": -0.5223412}, {"type": "node", "id": 2499901516, "lat": 44.8636679, "lon": -0.5219962}, {"type": "node", "id": 2499901518, "lat": 44.8636286, "lon": -0.5226249}, {"type": "node", "id": 2499901530, "lat": 44.8637541, "lon": -0.5223699}, {"type": "node", "id": 2499901536, "lat": 44.8637793, "lon": -0.522012}, {"type": "node", "id": 2499901539, "lat": 44.863732, "lon": -0.5226348}, {"type": "node", "id": 2499901544, "lat": 44.8637408, "lon": -0.5213299}, {"type": "node", "id": 2499901551, "lat": 44.8638497, "lon": -0.5213761}, {"type": "node", "id": 2499901554, "lat": 44.8638721, "lon": -0.52073}, {"type": "node", "id": 2499901556, "lat": 44.8639282, "lon": -0.5205218}, {"type": "node", "id": 2499901562, "lat": 44.863984, "lon": -0.5208783}, {"type": "node", "id": 2499901565, "lat": 44.8640252, "lon": -0.520793}, {"type": "node", "id": 2499901567, "lat": 44.863941, "lon": -0.5209863}, {"type": "node", "id": 2499901570, "lat": 44.8641907, "lon": -0.5205752}, {"type": "node", "id": 2499901572, "lat": 44.8639691, "lon": -0.5202793, "tags": {"direction": "forward", "highway": "give_way"}}, {"type": "node", "id": 2499901575, "lat": 44.8639563, "lon": -0.5203789}, {"type": "node", "id": 2501126313, "lat": 44.8646172, "lon": -0.5183567}, {"type": "node", "id": 2501126315, "lat": 44.8641649, "lon": -0.519639}, {"type": "node", "id": 2501126316, "lat": 44.8645064, "lon": -0.5183006}, {"type": "node", "id": 2501799493, "lat": 44.8641004, "lon": -0.5206773}, {"type": "node", "id": 2503641858, "lat": 44.8642736, "lon": -0.5197234, "tags": {"crossing": "uncontrolled", "highway": "crossing"}}, {"type": "node", "id": 2503641859, "lat": 44.8642867, "lon": -0.5198254, "tags": {"direction": "forward", "highway": "give_way"}}, {"type": "node", "id": 2503641861, "lat": 44.8641484, "lon": -0.5197017, "tags": {"crossing": "uncontrolled", "highway": "crossing"}}, {"type": "node", "id": 2503641862, "lat": 44.8641152, "lon": -0.5197932}, {"type": "node", "id": 2586377621, "lat": 44.8108541, "lon": -0.5332206}, {"type": "node", "id": 2586377623, "lat": 44.811275, "lon": -0.5335602}, {"type": "node", "id": 2586377625, "lat": 44.8106568, "lon": -0.5330941}, {"type": "node", "id": 2591488465, "lat": 44.8375262, "lon": -0.5499705}, {"type": "node", "id": 2591488467, "lat": 44.8373526, "lon": -0.5505847}, {"type": "node", "id": 2591488470, "lat": 44.8370923, "lon": -0.5510341}, {"type": "node", "id": 2591708342, "lat": 44.8373763, "lon": -0.5488925}, {"type": "node", "id": 2591708343, "lat": 44.8348201, "lon": -0.5499401}, {"type": "node", "id": 2591708344, "lat": 44.8345913, "lon": -0.5499361}, {"type": "node", "id": 2591708345, "lat": 44.8345191, "lon": -0.5499544}, {"type": "node", "id": 2591708346, "lat": 44.8344211, "lon": -0.5500096}, {"type": "node", "id": 2591708347, "lat": 44.8342566, "lon": -0.5502083}, {"type": "node", "id": 2591708348, "lat": 44.8340633, "lon": -0.5505183}, {"type": "node", "id": 2591708349, "lat": 44.8340366, "lon": -0.5505639, "tags": {"highway": "crossing"}}, {"type": "node", "id": 2591708352, "lat": 44.8347115, "lon": -0.5499196}, {"type": "node", "id": 2591721118, "lat": 44.830716, "lon": -0.5557937}, {"type": "node", "id": 2591721122, "lat": 44.8307154, "lon": -0.5558989}, {"type": "node", "id": 2591721125, "lat": 44.8307474, "lon": -0.5558361}, {"type": "node", "id": 2591814721, "lat": 44.8451577, "lon": -0.5391102}, {"type": "node", "id": 2591814723, "lat": 44.845543, "lon": -0.5390352}, {"type": "node", "id": 2591814726, "lat": 44.8452639, "lon": -0.5393218}, {"type": "node", "id": 2591814728, "lat": 44.8458094, "lon": -0.5388009}, {"type": "node", "id": 2611016493, "lat": 44.847171, "lon": -0.537669}, {"type": "node", "id": 2633435009, "lat": 44.8114487, "lon": -0.5336754}, {"type": "node", "id": 3516916209, "lat": 44.8462516, "lon": -0.5378652}, {"type": "node", "id": 3516916210, "lat": 44.8464536, "lon": -0.5377707, "tags": {"crossing": "traffic_signals", "highway": "crossing"}}, {"type": "node", "id": 3516916213, "lat": 44.8465109, "lon": -0.5377723}, {"type": "node", "id": 4026658834, "lat": 44.8359989, "lon": -0.5503668}, {"type": "node", "id": 4026658835, "lat": 44.8359957, "lon": -0.5505193}, {"type": "node", "id": 4109606869, "lat": 44.8359196, "lon": -0.5502318}, {"type": "node", "id": 4547996427, "lat": 44.8303025, "lon": -0.5554575}, {"type": "node", "id": 4547996428, "lat": 44.8300347, "lon": -0.5549362}, {"type": "node", "id": 4547996429, "lat": 44.8299076, "lon": -0.5547367}, {"type": "node", "id": 4547996430, "lat": 44.829816, "lon": -0.5546653}, {"type": "node", "id": 4547996431, "lat": 44.8307558, "lon": -0.5550916}, {"type": "node", "id": 5103462297, "lat": 44.8345951, "lon": -0.5500014}, {"type": "node", "id": 5103462298, "lat": 44.834409, "lon": -0.5501529}, {"type": "node", "id": 5103462316, "lat": 44.8343442, "lon": -0.5500998}, {"type": "node", "id": 5103462318, "lat": 44.8347145, "lon": -0.5499851}, {"type": "node", "id": 5103462319, "lat": 44.8348153, "lon": -0.5499988}, {"type": "node", "id": 5103462320, "lat": 44.8349333, "lon": -0.5500331}, {"type": "node", "id": 5103463421, "lat": 44.8356886, "lon": -0.550234}, {"type": "node", "id": 5103463422, "lat": 44.8345348, "lon": -0.5500293}, {"type": "node", "id": 5103463423, "lat": 44.8344601, "lon": -0.5500934}, {"type": "node", "id": 5103463424, "lat": 44.8357595, "lon": -0.5502488}, {"type": "node", "id": 5103463425, "lat": 44.8358051, "lon": -0.5502689}, {"type": "node", "id": 5103463426, "lat": 44.8354577, "lon": -0.5509404}, {"type": "node", "id": 5103463427, "lat": 44.836492, "lon": -0.5500092}, {"type": "node", "id": 5103531248, "lat": 44.8358356, "lon": -0.5503249}, {"type": "node", "id": 5104002358, "lat": 44.8358233, "lon": -0.5504905, "tags": {"highway": "traffic_signals", "traffic_signals": "signal", "traffic_signals:direction": "forward"}}, {"type": "node", "id": 5104002359, "lat": 44.8358453, "lon": -0.5504505}, {"type": "node", "id": 5104004311, "lat": 44.8354149, "lon": -0.5530218, "tags": {"highway": "traffic_signals", "traffic_signals": "signal", "traffic_signals:direction": "forward"}}, {"type": "node", "id": 5104004314, "lat": 44.8341125, "lon": -0.5506343, "tags": {"highway": "traffic_signals", "traffic_signals": "signal", "traffic_signals:direction": "forward"}}, {"type": "node", "id": 5274008583, "lat": 44.8445346, "lon": -0.5144923}, {"type": "node", "id": 5274008591, "lat": 44.844366, "lon": -0.5142369}, {"type": "node", "id": 5274008592, "lat": 44.8443182, "lon": -0.5147354}, {"type": "node", "id": 5274008593, "lat": 44.844349, "lon": -0.5144897}, {"type": "node", "id": 5274008594, "lat": 44.8443348, "lon": -0.5146156}, {"type": "node", "id": 5274008595, "lat": 44.8443587, "lon": -0.5143637}, {"type": "node", "id": 5274008596, "lat": 44.8442305, "lon": -0.515151}, {"type": "node", "id": 5274008597, "lat": 44.8442787, "lon": -0.5149455}, {"type": "node", "id": 5274008598, "lat": 44.8443001, "lon": -0.5148412}, {"type": "node", "id": 5274008600, "lat": 44.8445085, "lon": -0.5147239}, {"type": "node", "id": 5274008601, "lat": 44.8445456, "lon": -0.5142499}, {"type": "node", "id": 5274008605, "lat": 44.844456, "lon": -0.5149623}, {"type": "node", "id": 5274008606, "lat": 44.8444887, "lon": -0.5148417}, {"type": "node", "id": 5274008608, "lat": 44.8445383, "lon": -0.5138423}, {"type": "node", "id": 5520403056, "lat": 44.8376454, "lon": -0.5488421}, {"type": "node", "id": 5520403057, "lat": 44.8376038, "lon": -0.5487178}, {"type": "node", "id": 5520403058, "lat": 44.8375781, "lon": -0.5486969, "tags": {"highway": "traffic_signals"}}, {"type": "node", "id": 5520403059, "lat": 44.8375155, "lon": -0.5487052}, {"type": "node", "id": 5520403060, "lat": 44.8360924, "lon": -0.5503201, "tags": {"highway": "traffic_signals", "traffic_signals": "signal", "traffic_signals:direction": "forward"}}, {"type": "node", "id": 5547973830, "lat": 44.8358516, "lon": -0.5503722}, {"type": "node", "id": 5547973831, "lat": 44.8358542, "lon": -0.5504157}, {"type": "node", "id": 5547973833, "lat": 44.8358078, "lon": -0.5501823}, {"type": "node", "id": 5547973834, "lat": 44.8354627, "lon": -0.5501116}, {"type": "node", "id": 5547973835, "lat": 44.8354419, "lon": -0.5501712}, {"type": "node", "id": 5547973836, "lat": 44.8351197, "lon": -0.5500171}, {"type": "node", "id": 5547973837, "lat": 44.8351134, "lon": -0.5500823}, {"type": "node", "id": 5547973838, "lat": 44.8340976, "lon": -0.5504445}, {"type": "node", "id": 5547980964, "lat": 44.8341585, "lon": -0.5503395}, {"type": "node", "id": 5547980965, "lat": 44.8344696, "lon": -0.5499749}, {"type": "node", "id": 5547980966, "lat": 44.8344906, "lon": -0.5500628}, {"type": "node", "id": 5547980969, "lat": 44.8362157, "lon": -0.5502278}, {"type": "node", "id": 5547980970, "lat": 44.8361558, "lon": -0.5502874}, {"type": "node", "id": 5547989306, "lat": 44.8355919, "lon": -0.5507358}, {"type": "node", "id": 5547989307, "lat": 44.83566, "lon": -0.5506709}, {"type": "node", "id": 5547989308, "lat": 44.8357499, "lon": -0.5505706}, {"type": "node", "id": 5551010358, "lat": 44.8374719, "lon": -0.5487834}, {"type": "node", "id": 5551010365, "lat": 44.8375461, "lon": -0.5486882}, {"type": "node", "id": 5551010366, "lat": 44.837626, "lon": -0.548771}, {"type": "node", "id": 5551010370, "lat": 44.8360043, "lon": -0.5504411}, {"type": "node", "id": 5551010371, "lat": 44.8359642, "lon": -0.5502963}, {"type": "node", "id": 5632902107, "lat": 44.8642387, "lon": -0.5193607, "tags": {"bus": "yes", "public_transport": "stop_position"}}, {"type": "node", "id": 5632902108, "lat": 44.8643412, "lon": -0.5194556, "tags": {"bus": "yes", "public_transport": "stop_position"}}, {"type": "node", "id": 5735882286, "lat": 44.8239974, "lon": -0.5433761}, {"type": "node", "id": 5735882287, "lat": 44.8241421, "lon": -0.5436687, "tags": {"highway": "traffic_signals", "traffic_signals": "signal"}}, {"type": "node", "id": 5735882288, "lat": 44.8241677, "lon": -0.543776}, {"type": "node", "id": 5735882289, "lat": 44.8241849, "lon": -0.5439911}, {"type": "node", "id": 5735882290, "lat": 44.8241293, "lon": -0.5442109}, {"type": "node", "id": 5735882291, "lat": 44.8241652, "lon": -0.5440994}, {"type": "node", "id": 5735882292, "lat": 44.8241844, "lon": -0.5438689}, {"type": "node", "id": 5911304588, "lat": 44.8310816, "lon": -0.5571454}, {"type": "node", "id": 6376101488, "lat": 44.8467551, "lon": -0.5374012, "tags": {"crossing": "uncontrolled", "highway": "crossing"}}, {"type": "node", "id": 6376101489, "lat": 44.8467934, "lon": -0.5374797}, {"type": "node", "id": 6376101498, "lat": 44.846401, "lon": -0.5377914, "tags": {"highway": "traffic_signals", "traffic_signals": "signal", "traffic_signals:direction": "forward"}}, {"type": "node", "id": 6376101499, "lat": 44.846404, "lon": -0.5376851, "tags": {"highway": "traffic_signals", "traffic_signals": "signal", "traffic_signals:direction": "forward"}}, {"type": "node", "id": 6376101512, "lat": 44.8467352, "lon": -0.539319}, {"type": "node", "id": 6376101514, "lat": 44.8465157, "lon": -0.538994}, {"type": "node", "id": 6376101515, "lat": 44.8471911, "lon": -0.5388044}, {"type": "node", "id": 6376101525, "lat": 44.846515, "lon": -0.5362613}, {"type": "node", "id": 6572570365, "lat": 44.8442478, "lon": -0.5116259}, {"type": "node", "id": 7160858650, "lat": 44.8637268, "lon": -0.5234166}, {"type": "node", "id": 7160858651, "lat": 44.8636316, "lon": -0.5234231}, {"type": "node", "id": 7166994952, "lat": 44.8645375, "lon": -0.5186687}, {"type": "node", "id": 7166994955, "lat": 44.8644322, "lon": -0.5185969}, {"type": "node", "id": 7166994957, "lat": 44.8647498, "lon": -0.517693}, {"type": "node", "id": 7179379998, "lat": 44.8146932, "lon": -0.5725999}, {"type": "node", "id": 8537049170, "lat": 44.8146989, "lon": -0.5724355, "tags": {"highway": "traffic_signals", "traffic_signals": "signal", "traffic_signals:direction": "forward"}}, {"type": "node", "id": 8537049171, "lat": 44.8146939, "lon": -0.5723841}, {"type": "node", "id": 8599718360, "lat": 44.8374121, "lon": -0.550421}, {"type": "node", "id": 9060400535, "lat": 44.8301359, "lon": -0.5535716}, {"type": "node", "id": 9060400536, "lat": 44.8294169, "lon": -0.5521828}, {"type": "node", "id": 9060400537, "lat": 44.8291751, "lon": -0.5517191}, {"type": "node", "id": 9060400538, "lat": 44.8287173, "lon": -0.550919}, {"type": "node", "id": 9060400539, "lat": 44.827808, "lon": -0.5493505}, {"type": "node", "id": 9060400540, "lat": 44.8268811, "lon": -0.5478049}, {"type": "way", "id": 5117198, "nodes": [35232813, 2591721125, 2591721122, 1981045090, 1673087236, 1981045084, 1673087221, 1981045063, 1673087274, 1981045086, 1673087275, 1673087276, 1673087272, 1673087262, 1673087241, 1673087233, 1673087252, 1673087229, 1673087232, 1673087234, 1673087265, 1673087258, 1981045154, 1673087277, 1673087267, 1581075092, 4547996431, 1981045038, 9060400535, 9060400536, 9060400537, 9060400538, 9060400539, 9060400540, 1979289525], "tags": {"highway": "primary_link", "lanes": "1", "maxspeed": "30", "oneway": "yes"}}, {"type": "way", "id": 5117201, "nodes": [35232813, 2591721118, 1581075072, 1981045066, 1981045059, 1981045053, 1581075083, 1981045046, 35232824], "tags": {"highway": "primary_link", "lanes": "2", "maxspeed": "30", "oneway": "yes"}}, {"type": "way", "id": 5117207, "nodes": [35232824, 1581075081, 1981045091, 35232825, 1581075033, 35232826, 1981045135], "tags": {"highway": "primary_link", "lanes": "1", "oneway": "yes"}}, {"type": "way", "id": 5117329, "nodes": [35234387, 5520403056, 1037550007, 2591488465, 35234867, 1037549996, 8599718360, 2591488467, 35234871, 2591488470, 288513883, 1581019343], "tags": {"highway": "primary_link", "lanes": "1", "oneway": "yes", "source": "Bing"}}, {"type": "way", "id": 5117431, "nodes": [35238005, 2493896459, 35238009, 35238012, 35238014, 35238017, 35238019, 2493896473, 35238023, 35238026, 35238029, 35238032, 2493896472, 35238034, 35238036, 35238040, 35238043], "tags": {"highway": "primary_link", "oneway": "yes"}}, {"type": "way", "id": 5117433, "nodes": [35237795, 6376101525, 2493901269, 35238061], "tags": {"highway": "primary_link", "oneway": "yes", "surface": "asphalt"}}, {"type": "way", "id": 5117435, "nodes": [35238043, 35238045, 2493896474, 6376101512, 35238048, 2493896475, 35238050, 35237815], "tags": {"highway": "primary_link", "oneway": "yes"}}, {"type": "way", "id": 5117439, "nodes": [35234319, 2591814721, 35237943, 35237945, 35237949, 35237952, 3516916209, 6376101499, 35237955, 2493901289, 35237885], "tags": {"highway": "primary_link", "oneway": "yes"}}, {"type": "way", "id": 5117440, "nodes": [3516916209, 6376101498, 3516916210, 3516916213], "tags": {"highway": "primary_link", "oneway": "yes"}}, {"type": "way", "id": 5117450, "nodes": [35237868, 35237917, 2495308369, 35237920, 2495308371, 2495308361, 35237925, 2495308363, 35237929, 2495308365, 35237933, 2495308367, 35237936, 2591814723], "tags": {"highway": "primary_link", "oneway": "yes"}}, {"type": "way", "id": 5117453, "nodes": [35238043, 35238054, 2493896477, 35238058, 6376101514, 35237812, 2495308373, 35237872], "tags": {"highway": "primary_link", "oneway": "yes"}}, {"type": "way", "id": 23448826, "nodes": [253946791, 1978021383, 253946802, 1978021388, 1222773156, 253946803, 1978021386, 253946804], "tags": {"bicycle": "no", "destination": "M\u00e9rignac;Rocade;B\u00e8gles", "foot": "no", "highway": "primary_link", "horse": "no", "oneway": "yes", "surface": "asphalt"}}, {"type": "way", "id": 24056350, "nodes": [260953262, 2496127699, 2496127700, 2496121535, 2496121548, 6572570365, 1471045243, 2496121518, 1471045251, 1471045256, 5274008608, 1471045258, 5274008601, 5274008583, 5274008600, 5274008606, 5274008605, 260953219], "tags": {"highway": "primary_link", "oneway": "yes"}}, {"type": "way", "id": 24056369, "nodes": [260354823, 5274008596, 5274008597, 5274008598, 5274008592, 5274008594, 5274008593, 5274008595, 5274008591, 1471045240, 2496121509, 2496121514, 1471045227, 2496121531, 2496121541, 2496127698, 2496127697, 260953381], "tags": {"highway": "primary_link", "oneway": "yes"}}, {"type": "way", "id": 24056376, "nodes": [260354778, 2496135810, 260954203, 2496135808, 1471045219, 2496127702, 2496127701, 260953380], "tags": {"highway": "primary_link", "oneway": "yes"}}, {"type": "way", "id": 24056388, "nodes": [260953379, 2496127703, 2496127704, 2496121553, 2496135807, 1471045162, 2496135809, 260954019], "tags": {"highway": "primary_link", "oneway": "yes"}}, {"type": "way", "id": 25688958, "nodes": [35237958, 35237960], "tags": {"highway": "primary_link", "maxheight": "4.8", "name": "Boulevard Joliot-Curie", "oneway": "yes"}}, {"type": "way", "id": 25725963, "nodes": [280519104, 7166994957, 2501126313, 7166994952, 5632902108, 2503641858, 476668275, 2503641859, 280518943], "tags": {"highway": "primary_link", "lanes": "1", "maxspeed": "50", "oneway": "yes", "source": "Bing", "surface": "asphalt"}}, {"type": "way", "id": 26143094, "nodes": [1981045135, 35232827, 1981045194, 35232829, 1981045234, 35232795], "tags": {"highway": "primary_link", "lanes": "2", "oneway": "yes"}}, {"type": "way", "id": 26143098, "nodes": [35232824, 1981045056, 1581075052, 35232830, 1981045101, 1981045108], "tags": {"highway": "primary_link", "lanes": "1", "oneway": "yes"}}, {"type": "way", "id": 26300872, "nodes": [1673097815, 2591708349, 2591708348, 5547973838, 5547980964, 2591708347, 5103462316, 2591708346, 5547980965, 2591708345, 2591708344, 2591708352, 2591708343, 1673097830, 5547973836, 5547973834, 1673097827, 5547973833, 288123369, 4109606869, 5551010371, 4026658834], "tags": {"highway": "primary_link", "lanes": "2", "maxspeed": "50", "oneway": "yes"}}, {"type": "way", "id": 26515979, "nodes": [280518936, 2499901570, 2501799493, 290613159, 2499901565, 2499901562, 2499901567, 290613211, 2499901551, 570287345, 2499901536, 2499901530, 2499901539, 2499901482, 2499901494, 7160858650, 2499901497, 290613161], "tags": {"highway": "primary_link", "lanes": "1", "maxspeed": "50", "oneway": "yes", "source": "Bing", "surface": "asphalt"}}, {"type": "way", "id": 26515995, "nodes": [570287359, 2503641862, 476668563, 2503641861, 2501126315, 5632902107, 7166994955, 2501126316, 290613280], "tags": {"highway": "primary_link", "lanes": "1", "maxspeed": "50", "oneway": "yes", "source": "Bing", "surface": "asphalt"}}, {"type": "way", "id": 35049305, "nodes": [35238003, 411082311], "tags": {"bridge": "yes", "highway": "primary_link", "layer": "1", "oneway": "yes"}}, {"type": "way", "id": 35049306, "nodes": [411082311, 2591814728, 2591814723, 2591814726, 35234366], "tags": {"highway": "primary_link", "oneway": "yes"}}, {"type": "way", "id": 36904354, "nodes": [1973883981, 417092258, 1973883978], "tags": {"highway": "primary_link", "lanes": "2", "lit": "yes", "maxspeed": "50", "surface": "asphalt"}}, {"type": "way", "id": 44981564, "nodes": [570287339, 7160858651, 2499901504, 2499901499, 2499901518, 2499901514, 2499901516, 570287347, 2499901544, 570287351, 2499901554, 2499901556, 2499901575, 2499901572, 570287353], "tags": {"highway": "primary_link", "lanes": "1", "maxspeed": "50", "oneway": "yes", "source": "Bing", "surface": "asphalt"}}, {"type": "way", "id": 47418387, "nodes": [5103463426, 5547989306, 5547989307, 5547989308, 5104002358, 5104002359, 5547973831, 5547973830, 5103531248, 5103463425], "tags": {"highway": "primary_link", "oneway": "yes"}}, {"type": "way", "id": 71327155, "nodes": [280478284, 2586377621, 2586377625, 257740410], "tags": {"bicycle": "no", "foot": "no", "highway": "primary_link", "horse": "no", "lanes": "1", "motorroad": "yes", "surface": "asphalt"}}, {"type": "way", "id": 106218983, "nodes": [1222773167, 1222773153, 1222773154, 1978021413, 1222773157, 1222773161, 253946793], "tags": {"highway": "primary_link", "lanes": "1", "oneway": "yes", "surface": "asphalt"}}, {"type": "way", "id": 133758481, "nodes": [279709943, 35232840, 35232841, 4547996430, 1472201150, 4547996429, 35232842, 4547996428, 35232843, 35232844, 4547996427, 35232845, 1981045036, 1581062441, 1981045040, 1581062466, 35232846], "tags": {"highway": "primary_link", "lanes": "2", "maxspeed": "30", "oneway": "yes"}}, {"type": "way", "id": 155136077, "nodes": [35237960, 2493896480, 35237964, 2493896479, 35237968, 2493896478, 35237971, 2493896476, 35237973, 35237977, 35237980, 6376101515, 2493896471, 35237982, 35237985, 2493896470, 35237988, 2493896469, 35237991, 2493896468, 35237994, 35237997, 35238000, 35238003], "tags": {"highway": "primary_link", "oneway": "yes"}}, {"type": "way", "id": 155136079, "nodes": [35238061, 35238066], "tags": {"highway": "primary_link", "maxheight": "4.8", "oneway": "yes"}}, {"type": "way", "id": 155136088, "nodes": [35238066, 2493901267, 6376101488, 6376101489, 2493901265, 35238068, 35238071, 35238075, 2493896465, 2611016493, 35238077, 2493896464, 35234327], "tags": {"highway": "primary_link", "oneway": "yes"}}, {"type": "way", "id": 183171421, "nodes": [272268764, 1935345768, 8537049171, 8537049170, 1935345787, 7179379998, 1935345785, 1973883978], "tags": {"highway": "primary_link", "lanes": "1", "lit": "yes", "maxspeed": "50", "oneway": "yes", "surface": "asphalt", "turn:lanes": "left"}}, {"type": "way", "id": 187403222, "nodes": [35232795, 1981045256, 1981045282, 35232802], "tags": {"highway": "primary_link", "lanes": "2", "oneway": "yes", "surface": "asphalt"}}, {"type": "way", "id": 306411520, "nodes": [1581019343, 915926782, 5104004311, 1673104946, 35234874], "tags": {"highway": "primary_link", "lanes": "2", "oneway": "yes", "source": "Bing"}}, {"type": "way", "id": 306411522, "nodes": [1981045108, 5911304588], "tags": {"highway": "primary_link", "lanes": "2", "oneway": "yes"}}, {"type": "way", "id": 400034377, "nodes": [4026658834, 5551010370, 4026658835], "tags": {"highway": "primary_link", "maxspeed": "50", "oneway": "yes"}}, {"type": "way", "id": 524424924, "nodes": [5103463427, 5547980969, 5547980970, 5520403060, 4026658834], "tags": {"highway": "primary_link", "oneway": "yes"}}, {"type": "way", "id": 524491803, "nodes": [5103463425, 5103463424, 5103463421, 5547973835, 5547973837, 5103462320, 5103462319, 5103462318, 5103462297, 5103463422, 5547980966, 5103463423, 5103462298, 1673093267, 1673093260, 1673093256, 1673093317, 5104004314, 1673093169, 35234833], "tags": {"highway": "primary_link", "lanes": "2", "oneway": "yes"}}, {"type": "way", "id": 535285198, "nodes": [2633435009, 2586377623, 280478284], "tags": {"highway": "primary_link", "lanes": "1", "surface": "asphalt"}}, {"type": "way", "id": 575262615, "nodes": [2591708342, 5551010358, 5520403059, 5551010365, 5520403058, 5520403057, 5551010366, 5520403056], "tags": {"highway": "primary_link", "note": "fixme - approx position", "oneway": "yes"}}, {"type": "way", "id": 575262616, "nodes": [4026658834, 5103463425], "tags": {"highway": "primary_link", "oneway": "yes"}}, {"type": "way", "id": 604518780, "nodes": [5735882286, 5735882287, 5735882288, 5735882292, 5735882289, 5735882291, 5735882290, 1978021394], "tags": {"bicycle": "no", "foot": "no", "highway": "primary_link", "horse": "no", "oneway": "yes", "surface": "asphalt"}}, {"type": "way", "id": 626141638, "nodes": [5911304588, 35232833, 1981045211, 1581075094, 1981045235, 35232797], "tags": {"highway": "primary_link", "lanes": "3", "oneway": "yes"}}, {"type": "way", "id": 708309470, "nodes": [21459451, 1979396449, 279709943], "tags": {"highway": "primary_link", "lanes": "2", "maxspeed": "30", "oneway": "yes"}}]}