{"version": 0.6, "generator": "Overpass API 0.7.57 93a4d346", "osm3s": {"timestamp_osm_base": "2022-01-17T16:21:11Z", "copyright": "The data included in this document is from www.openstreetmap.org. The data is made available under ODbL."}, "elements": [{"type": "node", "id": 21459444, "lat": 44.8316119, "lon": -0.558558}, {"type": "node", "id": 25214067, "lat": 44.8768044, "lon": -0.6220915}, {"type": "node", "id": 35232776, "lat": 44.8315188, "lon": -0.5586703}, {"type": "node", "id": 35232800, "lat": 44.8317835, "lon": -0.5581463}, {"type": "node", "id": 35232801, "lat": 44.8317129, "lon": -0.5584224}, {"type": "node", "id": 229911115, "lat": 44.8449741, "lon": -0.5706978}, {"type": "node", "id": 240713647, "lat": 44.7913036, "lon": -0.6052769}, {"type": "node", "id": 244117768, "lat": 44.8171348, "lon": -0.5484911, "tags": {"highway": "traffic_signals"}}, {"type": "node", "id": 244117784, "lat": 44.8466512, "lon": -0.5981412, "tags": {"highway": "traffic_signals"}}, {"type": "node", "id": 244117785, "lat": 44.8482214, "lon": -0.5975169, "tags": {"highway": "traffic_signals"}}, {"type": "node", "id": 244645764, "lat": 44.8703068, "lon": -0.5665757}, {"type": "node", "id": 247888382, "lat": 44.8765612, "lon": -0.5769014}, {"type": "node", "id": 247888815, "lat": 44.8772435, "lon": -0.5765208}, {"type": "node", "id": 247888817, "lat": 44.877046, "lon": -0.5769606}, {"type": "node", "id": 247888818, "lat": 44.8770827, "lon": -0.5771854}, {"type": "node", "id": 247888881, "lat": 44.8773536, "lon": -0.576607}, {"type": "node", "id": 247888882, "lat": 44.8772005, "lon": -0.5769794}, {"type": "node", "id": 247888883, "lat": 44.877159, "lon": -0.5770203}, {"type": "node", "id": 247888884, "lat": 44.876974, "lon": -0.5770372}, {"type": "node", "id": 247888947, "lat": 44.8771318, "lon": -0.5775033}, {"type": "node", "id": 247889069, "lat": 44.8739956, "lon": -0.5762994}, {"type": "node", "id": 247889158, "lat": 44.8739681, "lon": -0.5768376}, {"type": "node", "id": 249799832, "lat": 44.8698386, "lon": -0.5664305}, {"type": "node", "id": 249810951, "lat": 44.8699701, "lon": -0.5661164}, {"type": "node", "id": 249810952, "lat": 44.8702582, "lon": -0.5659376, "tags": {"highway": "traffic_signals", "traffic_signals": "signal", "traffic_signals:direction": "forward"}}, {"type": "node", "id": 250165568, "lat": 44.8393883, "lon": -0.5872944, "tags": {"highway": "traffic_signals"}}, {"type": "node", "id": 250166082, "lat": 44.8569416, "lon": -0.5910848}, {"type": "node", "id": 250166198, "lat": 44.8454586, "lon": -0.5935858}, {"type": "node", "id": 250181956, "lat": 44.8414378, "lon": -0.599327}, {"type": "node", "id": 250207091, "lat": 44.841988, "lon": -0.5993828, "tags": {"highway": "traffic_signals"}}, {"type": "node", "id": 250224775, "lat": 44.8550217, "lon": -0.5717966}, {"type": "node", "id": 250287591, "lat": 44.8361069, "lon": -0.5824668}, {"type": "node", "id": 250288068, "lat": 44.8279699, "lon": -0.59313, "tags": {"highway": "traffic_signals"}}, {"type": "node", "id": 250311318, "lat": 44.839797, "lon": -0.5863358}, {"type": "node", "id": 250371530, "lat": 44.8377444, "lon": -0.5885363}, {"type": "node", "id": 250601669, "lat": 44.8274677, "lon": -0.5923837, "tags": {"highway": "traffic_signals"}}, {"type": "node", "id": 250601935, "lat": 44.8592171, "lon": -0.5894111}, {"type": "node", "id": 251538819, "lat": 44.8380593, "lon": -0.5860091, "tags": {"highway": "traffic_signals"}}, {"type": "node", "id": 255701980, "lat": 44.8418911, "lon": -0.5994863, "tags": {"highway": "traffic_signals"}}, {"type": "node", "id": 258075188, "lat": 44.8400527, "lon": -0.5689763}, {"type": "node", "id": 258606849, "lat": 44.838604, "lon": -0.5587865}, {"type": "node", "id": 259187477, "lat": 44.8372218, "lon": -0.5900017}, {"type": "node", "id": 260354794, "lat": 44.8451963, "lon": -0.5322686}, {"type": "node", "id": 260950544, "lat": 44.8212954, "lon": -0.5830773}, {"type": "node", "id": 261591344, "lat": 44.8134953, "lon": -0.5646839, "tags": {"highway": "traffic_signals"}}, {"type": "node", "id": 279121323, "lat": 44.8072243, "lon": -0.6008222}, {"type": "node", "id": 279706833, "lat": 44.8313885, "lon": -0.5588266}, {"type": "node", "id": 279815651, "lat": 44.8456728, "lon": -0.5330656}, {"type": "node", "id": 279815680, "lat": 44.8450489, "lon": -0.5324154}, {"type": "node", "id": 279815681, "lat": 44.8451098, "lon": -0.532334}, {"type": "node", "id": 279815688, "lat": 44.8455131, "lon": -0.5327035}, {"type": "node", "id": 279816868, "lat": 44.8456611, "lon": -0.532988}, {"type": "node", "id": 279816876, "lat": 44.8450726, "lon": -0.5326992}, {"type": "node", "id": 279816879, "lat": 44.8454781, "lon": -0.5326161}, {"type": "node", "id": 279816880, "lat": 44.8456345, "lon": -0.5328894}, {"type": "node", "id": 279898688, "lat": 44.8336228, "lon": -0.5500315, "tags": {"highway": "traffic_signals"}}, {"type": "node", "id": 280467913, "lat": 44.8168476, "lon": -0.5760615}, {"type": "node", "id": 280726298, "lat": 44.8308082, "lon": -0.5446313}, {"type": "node", "id": 280726302, "lat": 44.8307556, "lon": -0.5446864}, {"type": "node", "id": 280738634, "lat": 44.8170602, "lon": -0.5484771, "tags": {"highway": "traffic_signals"}}, {"type": "node", "id": 280951023, "lat": 44.866009, "lon": -0.5612115}, {"type": "node", "id": 281029428, "lat": 44.8401274, "lon": -0.5687638}, {"type": "node", "id": 281030228, "lat": 44.8449888, "lon": -0.5705731}, {"type": "node", "id": 282073664, "lat": 44.8549447, "lon": -0.5717062}, {"type": "node", "id": 282734521, "lat": 44.8054781, "lon": -0.5728041}, {"type": "node", "id": 288948521, "lat": 44.8525027, "lon": -0.5234262}, {"type": "node", "id": 290428894, "lat": 44.8456474, "lon": -0.5329346, "tags": {"highway": "crossing"}}, {"type": "node", "id": 417092247, "lat": 44.848242, "lon": -0.5975723, "tags": {"highway": "motorway_junction", "name": "Barri\u00e8re Saint-M\u00e9dard"}}, {"type": "node", "id": 417092259, "lat": 44.8134307, "lon": -0.5646666, "tags": {"highway": "motorway_junction", "name": "Barri\u00e8re de B\u00e8gles"}}, {"type": "node", "id": 476645657, "lat": 44.8618699, "lon": -0.5199389, "tags": {"highway": "traffic_signals"}}, {"type": "node", "id": 476646639, "lat": 44.8618626, "lon": -0.5197774, "tags": {"highway": "traffic_signals"}}, {"type": "node", "id": 533634092, "lat": 44.8376346, "lon": -0.5884672}, {"type": "node", "id": 533634094, "lat": 44.8379182, "lon": -0.5859855, "tags": {"highway": "traffic_signals"}}, {"type": "node", "id": 534588682, "lat": 44.8770457, "lon": -0.5770467}, {"type": "node", "id": 534588683, "lat": 44.8772318, "lon": -0.5769185}, {"type": "node", "id": 534588684, "lat": 44.8770908, "lon": -0.5767376}, {"type": "node", "id": 632233820, "lat": 44.8278982, "lon": -0.5932518, "tags": {"highway": "traffic_signals"}}, {"type": "node", "id": 632233861, "lat": 44.8274479, "lon": -0.5925766, "tags": {"highway": "traffic_signals"}}, {"type": "node", "id": 643735936, "lat": 44.8742332, "lon": -0.6185879}, {"type": "node", "id": 705814617, "lat": 44.8336961, "lon": -0.550378}, {"type": "node", "id": 1706026011, "lat": 44.8382026, "lon": -0.5580494}, {"type": "node", "id": 1706026017, "lat": 44.8386972, "lon": -0.5587637}, {"type": "node", "id": 1879102345, "lat": 44.8701481, "lon": -0.565925}, {"type": "node", "id": 1879167941, "lat": 44.8661204, "lon": -0.5610378}, {"type": "node", "id": 1879234155, "lat": 44.8700317, "lon": -0.5666008}, {"type": "node", "id": 1907088844, "lat": 44.8312001, "lon": -0.5579627}, {"type": "node", "id": 1909825181, "lat": 44.8361696, "lon": -0.5824535}, {"type": "node", "id": 1909825185, "lat": 44.8361965, "lon": -0.582432}, {"type": "node", "id": 1909825189, "lat": 44.8362407, "lon": -0.5823058}, {"type": "node", "id": 1923713407, "lat": 44.8361378, "lon": -0.582466}, {"type": "node", "id": 1932291171, "lat": 44.8164603, "lon": -0.5752957}, {"type": "node", "id": 1932291173, "lat": 44.8165421, "lon": -0.5754681}, {"type": "node", "id": 1932291175, "lat": 44.8168229, "lon": -0.575919}, {"type": "node", "id": 1932291177, "lat": 44.816844, "lon": -0.5759616, "tags": {"crossing": "traffic_signals", "crossing_ref": "zebra", "highway": "crossing"}}, {"type": "node", "id": 1935345836, "lat": 44.8168924, "lon": -0.5761306}, {"type": "node", "id": 1935345850, "lat": 44.8169705, "lon": -0.5760265}, {"type": "node", "id": 1936486452, "lat": 44.8132312, "lon": -0.5631818}, {"type": "node", "id": 1936486454, "lat": 44.813287, "lon": -0.5637349}, {"type": "node", "id": 1936486464, "lat": 44.8134003, "lon": -0.564601}, {"type": "node", "id": 1936486466, "lat": 44.8134099, "lon": -0.5645183, "tags": {"crossing": "traffic_signals", "crossing_ref": "zebra", "highway": "crossing"}}, {"type": "node", "id": 1936486468, "lat": 44.8134558, "lon": -0.5647717}, {"type": "node", "id": 1936486469, "lat": 44.8134637, "lon": -0.5648539, "tags": {"crossing": "traffic_signals", "crossing_ref": "zebra", "highway": "crossing"}}, {"type": "node", "id": 1936486480, "lat": 44.8134725, "lon": -0.564714}, {"type": "node", "id": 1936486486, "lat": 44.81353, "lon": -0.5652642}, {"type": "node", "id": 1942801227, "lat": 44.8700548, "lon": -0.5660058}, {"type": "node", "id": 1942801229, "lat": 44.8702018, "lon": -0.5659205}, {"type": "node", "id": 1942801232, "lat": 44.8703163, "lon": -0.5659817}, {"type": "node", "id": 1942801246, "lat": 44.8717455, "lon": -0.5660193}, {"type": "node", "id": 1946032483, "lat": 44.8699149, "lon": -0.5665402, "tags": {"highway": "traffic_signals", "traffic_signals": "signal", "traffic_signals:direction": "forward"}}, {"type": "node", "id": 1947667703, "lat": 44.8766699, "lon": -0.5769203}, {"type": "node", "id": 1947667706, "lat": 44.8767802, "lon": -0.5769658}, {"type": "node", "id": 1947667707, "lat": 44.876868, "lon": -0.5770075}, {"type": "node", "id": 1947667713, "lat": 44.8771156, "lon": -0.5766893}, {"type": "node", "id": 1947667714, "lat": 44.8771179, "lon": -0.5773339}, {"type": "node", "id": 1947667717, "lat": 44.8772073, "lon": -0.5765634}, {"type": "node", "id": 1947667728, "lat": 44.8773388, "lon": -0.5764164}, {"type": "node", "id": 1947667742, "lat": 44.877461, "lon": -0.5761969}, {"type": "node", "id": 1947667746, "lat": 44.8775268, "lon": -0.5762596}, {"type": "node", "id": 1952403443, "lat": 44.8770272, "lon": -0.5770469}, {"type": "node", "id": 1952403444, "lat": 44.8770506, "lon": -0.5768859}, {"type": "node", "id": 1952403445, "lat": 44.8770682, "lon": -0.5767962}, {"type": "node", "id": 1952403446, "lat": 44.8770506, "lon": -0.5770802, "tags": {"direction": "forward", "highway": "give_way"}}, {"type": "node", "id": 1952403448, "lat": 44.8771084, "lon": -0.577043}, {"type": "node", "id": 1952403449, "lat": 44.8771569, "lon": -0.5766242}, {"type": "node", "id": 1952403457, "lat": 44.8773852, "lon": -0.5763431}, {"type": "node", "id": 1955022671, "lat": 44.8682128, "lon": -0.5703599}, {"type": "node", "id": 1955022672, "lat": 44.8682431, "lon": -0.5703255}, {"type": "node", "id": 1955022674, "lat": 44.8683213, "lon": -0.5701522}, {"type": "node", "id": 1955022675, "lat": 44.8684904, "lon": -0.5697593}, {"type": "node", "id": 1955022677, "lat": 44.868597, "lon": -0.5695691, "tags": {"crossing": "traffic_signals", "crossing_ref": "zebra", "highway": "crossing"}}, {"type": "node", "id": 1962719181, "lat": 44.8393217, "lon": -0.5872221, "tags": {"highway": "traffic_signals"}}, {"type": "node", "id": 1962719187, "lat": 44.8398153, "lon": -0.5865543}, {"type": "node", "id": 1968533244, "lat": 44.8592117, "lon": -0.58957}, {"type": "node", "id": 1969685531, "lat": 44.8531462, "lon": -0.5940418}, {"type": "node", "id": 1969685685, "lat": 44.8570652, "lon": -0.5911511}, {"type": "node", "id": 1969813994, "lat": 44.8525344, "lon": -0.5943592}, {"type": "node", "id": 1969814013, "lat": 44.8527849, "lon": -0.5942204}, {"type": "node", "id": 1969814015, "lat": 44.8530289, "lon": -0.5940571, "tags": {"highway": "traffic_signals", "traffic_signals": "signal", "traffic_signals:direction": "forward"}}, {"type": "node", "id": 1969814017, "lat": 44.8530832, "lon": -0.5940414, "tags": {"crossing": "traffic_signals", "crossing_ref": "zebra", "highway": "crossing"}}, {"type": "node", "id": 1969987848, "lat": 44.8466794, "lon": -0.5981588}, {"type": "node", "id": 1969987852, "lat": 44.8467511, "lon": -0.5981559, "tags": {"crossing": "uncontrolled", "crossing_ref": "zebra", "highway": "crossing"}}, {"type": "node", "id": 1969987860, "lat": 44.8469445, "lon": -0.5981021}, {"type": "node", "id": 1969987862, "lat": 44.8471616, "lon": -0.5979455}, {"type": "node", "id": 1969987863, "lat": 44.8471667, "lon": -0.598017}, {"type": "node", "id": 1969987864, "lat": 44.8473073, "lon": -0.5979348}, {"type": "node", "id": 1969987865, "lat": 44.847322, "lon": -0.5980137}, {"type": "node", "id": 1969987871, "lat": 44.8479513, "lon": -0.5976901}, {"type": "node", "id": 1969987872, "lat": 44.8480789, "lon": -0.5976499}, {"type": "node", "id": 1969987874, "lat": 44.8481408, "lon": -0.5976429, "tags": {"crossing": "uncontrolled", "crossing_ref": "zebra", "highway": "crossing"}}, {"type": "node", "id": 1969987882, "lat": 44.8482635, "lon": -0.5976331, "tags": {"highway": "traffic_signals"}}, {"type": "node", "id": 1970000856, "lat": 44.8414318, "lon": -0.5994432}, {"type": "node", "id": 1973883953, "lat": 44.8133693, "lon": -0.5646467, "tags": {"highway": "traffic_signals"}}, {"type": "node", "id": 1973883960, "lat": 44.8136367, "lon": -0.5661662, "tags": {"bus": "yes", "public_transport": "stop_position"}}, {"type": "node", "id": 1981045157, "lat": 44.8312482, "lon": -0.558069}, {"type": "node", "id": 1981045197, "lat": 44.8314384, "lon": -0.5583825, "tags": {"crossing": "marked", "crossing_ref": "zebra", "highway": "crossing"}}, {"type": "node", "id": 1981045238, "lat": 44.8316632, "lon": -0.5584982, "tags": {"crossing": "marked", "crossing_ref": "zebra", "highway": "crossing"}}, {"type": "node", "id": 1981045260, "lat": 44.831778, "lon": -0.5582504}, {"type": "node", "id": 1983051444, "lat": 44.8362233, "lon": -0.5823762}, {"type": "node", "id": 2000178060, "lat": 44.8372663, "lon": -0.5899917}, {"type": "node", "id": 2000178062, "lat": 44.8372919, "lon": -0.5899731}, {"type": "node", "id": 2000178065, "lat": 44.8373085, "lon": -0.589949}, {"type": "node", "id": 2000178067, "lat": 44.8373215, "lon": -0.5899242}, {"type": "node", "id": 2000287034, "lat": 44.8398113, "lon": -0.5863942}, {"type": "node", "id": 2000287035, "lat": 44.8398214, "lon": -0.586464}, {"type": "node", "id": 2000287036, "lat": 44.8398674, "lon": -0.586244}, {"type": "node", "id": 2000287041, "lat": 44.8399231, "lon": -0.586166}, {"type": "node", "id": 2000287044, "lat": 44.8399528, "lon": -0.5860817, "tags": {"button_operated": "no", "check_date:crossing": "2020-11-24", "crossing": "traffic_signals", "crossing_ref": "zebra", "highway": "crossing", "tactile_paving": "no", "traffic_signals:sound": "no", "traffic_signals:vibration": "no"}}, {"type": "node", "id": 2000287046, "lat": 44.839964, "lon": -0.5860321, "tags": {"highway": "traffic_signals", "traffic_signals": "signal"}}, {"type": "node", "id": 2000287047, "lat": 44.8399854, "lon": -0.5858812}, {"type": "node", "id": 2000287049, "lat": 44.8400299, "lon": -0.5853992}, {"type": "node", "id": 2000287051, "lat": 44.8400499, "lon": -0.5853208}, {"type": "node", "id": 2000287054, "lat": 44.8401024, "lon": -0.5852147}, {"type": "node", "id": 2022926567, "lat": 44.845531, "lon": -0.5935769, "tags": {"crossing": "traffic_signals", "crossing_ref": "zebra", "highway": "crossing"}}, {"type": "node", "id": 2022926576, "lat": 44.8456238, "lon": -0.593591}, {"type": "node", "id": 2053010663, "lat": 44.8681754, "lon": -0.5705434}, {"type": "node", "id": 2053010665, "lat": 44.8681817, "lon": -0.5704887}, {"type": "node", "id": 2066632855, "lat": 44.8400772, "lon": -0.5689066}, {"type": "node", "id": 2066632858, "lat": 44.8400905, "lon": -0.5688688}, {"type": "node", "id": 2072658463, "lat": 44.8361817, "lon": -0.5824472}, {"type": "node", "id": 2072658466, "lat": 44.8362076, "lon": -0.5824142}, {"type": "node", "id": 2072658522, "lat": 44.8376619, "lon": -0.5884844}, {"type": "node", "id": 2072658526, "lat": 44.8377154, "lon": -0.5885181}, {"type": "node", "id": 2072658552, "lat": 44.8379596, "lon": -0.5859924}, {"type": "node", "id": 2072658558, "lat": 44.8380191, "lon": -0.5860024}, {"type": "node", "id": 2073096182, "lat": 44.8372446, "lon": -0.5899998}, {"type": "node", "id": 2076358905, "lat": 44.8314081, "lon": -0.558803, "tags": {"railway": "tram_level_crossing"}}, {"type": "node", "id": 2076358908, "lat": 44.8314349, "lon": -0.5587709, "tags": {"railway": "tram_level_crossing"}}, {"type": "node", "id": 2206446256, "lat": 44.793346, "lon": -0.5322812}, {"type": "node", "id": 2206446261, "lat": 44.7933539, "lon": -0.5328648}, {"type": "node", "id": 2206446278, "lat": 44.7934472, "lon": -0.5336094}, {"type": "node", "id": 2206446283, "lat": 44.7934253, "lon": -0.5322979}, {"type": "node", "id": 2206446321, "lat": 44.7936552, "lon": -0.5344819, "tags": {"crossing": "uncontrolled", "highway": "crossing"}}, {"type": "node", "id": 2206446336, "lat": 44.7936371, "lon": -0.5347057}, {"type": "node", "id": 2206451258, "lat": 44.7935223, "lon": -0.532868}, {"type": "node", "id": 2206451259, "lat": 44.7937867, "lon": -0.5336559}, {"type": "node", "id": 2206451265, "lat": 44.79402, "lon": -0.5346268}, {"type": "node", "id": 2393739717, "lat": 44.7928321, "lon": -0.6051772, "tags": {"highway": "traffic_signals", "traffic_signals": "signal"}}, {"type": "node", "id": 2487877592, "lat": 44.8213357, "lon": -0.5828563}, {"type": "node", "id": 2496048872, "lat": 44.8450656, "lon": -0.5323868, "tags": {"highway": "traffic_signals", "traffic_signals": "signal", "traffic_signals:direction": "forward"}}, {"type": "node", "id": 2496048873, "lat": 44.8450395, "lon": -0.532462}, {"type": "node", "id": 2496048875, "lat": 44.8450555, "lon": -0.5325969}, {"type": "node", "id": 2503792341, "lat": 44.8618663, "lon": -0.5198798}, {"type": "node", "id": 2503792345, "lat": 44.8618652, "lon": -0.5198347}, {"type": "node", "id": 2518667367, "lat": 44.8075129, "lon": -0.6007254, "tags": {"crossing": "traffic_signals", "highway": "crossing", "mapillary": "ZZyCsUEwapArot5C9EofOA", "source:geometry": "Mapillary 2018-10-25", "survey:date": "2018-10-16", "tactile_paving": "yes"}}, {"type": "node", "id": 2518667368, "lat": 44.8075179, "lon": -0.6007984}, {"type": "node", "id": 2518667369, "lat": 44.807524, "lon": -0.6006328}, {"type": "node", "id": 2518667370, "lat": 44.8075316, "lon": -0.6008587}, {"type": "node", "id": 2518667371, "lat": 44.8075447, "lon": -0.6005656}, {"type": "node", "id": 2518667373, "lat": 44.8075927, "lon": -0.6004949}, {"type": "node", "id": 2586773596, "lat": 44.7939689, "lon": -0.5345352}, {"type": "node", "id": 2586773607, "lat": 44.7936536, "lon": -0.5346119}, {"type": "node", "id": 2587186537, "lat": 44.7936422, "lon": -0.5344013}, {"type": "node", "id": 2587186539, "lat": 44.7934907, "lon": -0.533816}, {"type": "node", "id": 2587186541, "lat": 44.7933988, "lon": -0.5333267}, {"type": "node", "id": 2587186555, "lat": 44.7935901, "lon": -0.5331216}, {"type": "node", "id": 2587186557, "lat": 44.7937338, "lon": -0.5334923}, {"type": "node", "id": 2587186559, "lat": 44.7935537, "lon": -0.5329981}, {"type": "node", "id": 2591466992, "lat": 44.8382622, "lon": -0.5582245}, {"type": "node", "id": 2591466993, "lat": 44.8383461, "lon": -0.5583631}, {"type": "node", "id": 2591466994, "lat": 44.8384442, "lon": -0.5584988, "tags": {"highway": "traffic_signals", "traffic_signals": "signal", "traffic_signals:direction": "forward"}}, {"type": "node", "id": 2591466995, "lat": 44.8386478, "lon": -0.5587611}, {"type": "node", "id": 2899175826, "lat": 44.793881, "lon": -0.5340028}, {"type": "node", "id": 2920318031, "lat": 44.798082, "lon": -0.6000314, "tags": {"highway": "traffic_signals", "traffic_signals": "signal"}}, {"type": "node", "id": 2920318035, "lat": 44.7968015, "lon": -0.602099, "tags": {"highway": "traffic_signals", "traffic_signals": "signal"}}, {"type": "node", "id": 2920476951, "lat": 44.7968675, "lon": -0.6022191, "tags": {"highway": "traffic_signals", "traffic_signals": "signal"}}, {"type": "node", "id": 2920505793, "lat": 44.7928967, "lon": -0.6053294, "tags": {"highway": "traffic_signals", "traffic_signals": "signal"}}, {"type": "node", "id": 2920560735, "lat": 44.7935248, "lon": -0.6052081}, {"type": "node", "id": 2920560737, "lat": 44.7930677, "lon": -0.6052176, "tags": {"crossing": "marked", "highway": "crossing"}}, {"type": "node", "id": 2920560738, "lat": 44.7929784, "lon": -0.6052338}, {"type": "node", "id": 2920569201, "lat": 44.7989693, "lon": -0.5987379}, {"type": "node", "id": 2920569203, "lat": 44.7981917, "lon": -0.5999372, "tags": {"crossing": "uncontrolled", "crossing_ref": "zebra", "highway": "crossing"}}, {"type": "node", "id": 2920570837, "lat": 44.7963442, "lon": -0.6026825}, {"type": "node", "id": 2920570838, "lat": 44.7965365, "lon": -0.6025314}, {"type": "node", "id": 2920570839, "lat": 44.7967533, "lon": -0.6022766, "tags": {"crossing": "uncontrolled", "crossing_ref": "zebra", "highway": "crossing"}}, {"type": "node", "id": 2920570840, "lat": 44.7968037, "lon": -0.60224}, {"type": "node", "id": 2920572129, "lat": 44.7920556, "lon": -0.6053127}, {"type": "node", "id": 2920572232, "lat": 44.7922386, "lon": -0.6053094}, {"type": "node", "id": 2920572233, "lat": 44.7926897, "lon": -0.6052729, "tags": {"crossing": "uncontrolled", "crossing_ref": "zebra", "highway": "crossing", "mapillary": "skV1730ubrf7civ2U_cDpA", "survey:date": "2018-12-11", "wheelchair": "yes"}}, {"type": "node", "id": 2920572234, "lat": 44.7927537, "lon": -0.6052666}, {"type": "node", "id": 3072882047, "lat": 44.8681656, "lon": -0.5703829, "tags": {"crossing": "traffic_signals", "crossing_ref": "zebra", "highway": "crossing"}}, {"type": "node", "id": 3114703871, "lat": 44.8017318, "lon": -0.5937862}, {"type": "node", "id": 3114703881, "lat": 44.8017627, "lon": -0.5938246}, {"type": "node", "id": 3140674006, "lat": 44.8073646, "lon": -0.6007394}, {"type": "node", "id": 3140674015, "lat": 44.8076683, "lon": -0.6003769}, {"type": "node", "id": 3177444135, "lat": 44.8054319, "lon": -0.5727116}, {"type": "node", "id": 3177444136, "lat": 44.805431, "lon": -0.5727578}, {"type": "node", "id": 3736801965, "lat": 44.7981184, "lon": -0.6000199}, {"type": "node", "id": 4063645075, "lat": 44.8168733, "lon": -0.5760395}, {"type": "node", "id": 4064981397, "lat": 44.8660796, "lon": -0.5613178}, {"type": "node", "id": 4088941767, "lat": 44.8660638, "lon": -0.5611261}, {"type": "node", "id": 4088941768, "lat": 44.8661334, "lon": -0.5612305}, {"type": "node", "id": 4132832753, "lat": 44.8054486, "lon": -0.5727924}, {"type": "node", "id": 4132832754, "lat": 44.8054377, "lon": -0.5727777}, {"type": "node", "id": 4391584443, "lat": 44.7925079, "lon": -0.6052929}, {"type": "node", "id": 4391584448, "lat": 44.7933021, "lon": -0.6051878}, {"type": "node", "id": 4391617365, "lat": 44.7984166, "lon": -0.599584}, {"type": "node", "id": 4414453218, "lat": 44.8213038, "lon": -0.5829542}, {"type": "node", "id": 4414848192, "lat": 44.8072967, "lon": -0.6007979}, {"type": "node", "id": 4414848193, "lat": 44.8073352, "lon": -0.6007761}, {"type": "node", "id": 4530261657, "lat": 44.8168923, "lon": -0.5761041}, {"type": "node", "id": 4530261658, "lat": 44.8169125, "lon": -0.5760247}, {"type": "node", "id": 4616284991, "lat": 44.7938501, "lon": -0.5338835}, {"type": "node", "id": 4616285012, "lat": 44.7939391, "lon": -0.5343938, "tags": {"crossing": "uncontrolled", "highway": "crossing"}}, {"type": "node", "id": 4895226290, "lat": 44.8167952, "lon": -0.575872, "tags": {"highway": "traffic_signals", "traffic_signals": "signal", "traffic_signals:direction": "forward"}}, {"type": "node", "id": 4907314594, "lat": 44.8314255, "lon": -0.5583607, "tags": {"highway": "traffic_signals", "traffic_signals": "signal", "traffic_signals:direction": "forward"}}, {"type": "node", "id": 4907314596, "lat": 44.8316786, "lon": -0.5584781, "tags": {"highway": "traffic_signals", "traffic_signals": "signal", "traffic_signals:direction": "forward"}}, {"type": "node", "id": 4914607060, "lat": 44.8703811, "lon": -0.5666447}, {"type": "node", "id": 4914607061, "lat": 44.8699435, "lon": -0.5665706}, {"type": "node", "id": 4914607100, "lat": 44.8699829, "lon": -0.5665851}, {"type": "node", "id": 5103462305, "lat": 44.833642, "lon": -0.5501682}, {"type": "node", "id": 5103462310, "lat": 44.8335232, "lon": -0.5500342, "tags": {"highway": "traffic_signals"}}, {"type": "node", "id": 5395132026, "lat": 44.868173, "lon": -0.5704197}, {"type": "node", "id": 5520355191, "lat": 44.838595, "lon": -0.5587166}, {"type": "node", "id": 5520355192, "lat": 44.8385612, "lon": -0.558656}, {"type": "node", "id": 5538220084, "lat": 44.8661888, "lon": -0.5611406}, {"type": "node", "id": 5911191755, "lat": 44.8314968, "lon": -0.5585014}, {"type": "node", "id": 5911304591, "lat": 44.8317494, "lon": -0.558344}, {"type": "node", "id": 6452092861, "lat": 44.8739774, "lon": -0.5766377}, {"type": "node", "id": 6452092868, "lat": 44.8739874, "lon": -0.5764512, "tags": {"highway": "traffic_signals", "traffic_signals": "signal", "traffic_signals:direction": "forward"}}, {"type": "node", "id": 6452092869, "lat": 44.8739737, "lon": -0.5767173, "tags": {"highway": "traffic_signals", "traffic_signals": "signal", "traffic_signals:direction": "backward"}}, {"type": "node", "id": 6452201372, "lat": 44.8774435, "lon": -0.5764112}, {"type": "node", "id": 6454638650, "lat": 44.8700603, "lon": -0.5667458}, {"type": "node", "id": 6454638652, "lat": 44.8712597, "lon": -0.5662697}, {"type": "node", "id": 6454638653, "lat": 44.870616, "lon": -0.5665392}, {"type": "node", "id": 6454638654, "lat": 44.8705756, "lon": -0.5665561}, {"type": "node", "id": 6454638655, "lat": 44.8704556, "lon": -0.5666115}, {"type": "node", "id": 6454638656, "lat": 44.8706453, "lon": -0.566527, "tags": {"highway": "traffic_signals", "traffic_signals": "signal", "traffic_signals:direction": "forward"}}, {"type": "node", "id": 6454878282, "lat": 44.8703493, "lon": -0.5660303}, {"type": "node", "id": 6454879385, "lat": 44.8700998, "lon": -0.5659569}, {"type": "node", "id": 6486480601, "lat": 44.8526908, "lon": -0.5233727}, {"type": "node", "id": 6572480351, "lat": 44.8450393, "lon": -0.5325276}, {"type": "node", "id": 6572480352, "lat": 44.8450368, "lon": -0.532491}, {"type": "node", "id": 6572482872, "lat": 44.8456078, "lon": -0.5328368}, {"type": "node", "id": 6583771547, "lat": 44.8315206, "lon": -0.5586112}, {"type": "node", "id": 6583771548, "lat": 44.831513, "lon": -0.5585539}, {"type": "node", "id": 6913967538, "lat": 44.8767883, "lon": -0.6224018}, {"type": "node", "id": 6917896358, "lat": 44.8743273, "lon": -0.618531, "tags": {"railway": "tram_level_crossing"}}, {"type": "node", "id": 6917896360, "lat": 44.8742978, "lon": -0.6185488, "tags": {"railway": "tram_level_crossing"}}, {"type": "node", "id": 6917896367, "lat": 44.8743765, "lon": -0.6185013}, {"type": "node", "id": 7006990517, "lat": 44.7915367, "lon": -0.6053294}, {"type": "node", "id": 7024349740, "lat": 44.7988299, "lon": -0.5988847}, {"type": "node", "id": 7069821676, "lat": 44.7933429, "lon": -0.5326646}, {"type": "node", "id": 7069821677, "lat": 44.7934721, "lon": -0.5326495}, {"type": "node", "id": 7069830997, "lat": 44.7933804, "lon": -0.5331654}, {"type": "node", "id": 7175406389, "lat": 44.8593645, "lon": -0.5894584}, {"type": "node", "id": 7179456582, "lat": 44.8075152, "lon": -0.6006943, "tags": {"highway": "traffic_signals", "traffic_signals": "signal", "traffic_signals:direction": "forward"}}, {"type": "node", "id": 9053962608, "lat": 44.8455719, "lon": -0.5935758}, {"type": "way", "id": 23155632, "nodes": [1962719181, 250165568], "tags": {"highway": "tertiary_link", "lane_markings": "no", "surface": "asphalt"}}, {"type": "way", "id": 23458676, "nodes": [1907088844, 1981045157, 4907314594, 1981045197, 5911191755, 6583771548, 6583771547, 35232776], "tags": {"highway": "tertiary_link", "lanes": "2", "oneway": "yes", "surface": "asphalt"}}, {"type": "way", "id": 23698962, "nodes": [244117785, 417092247, 1969987882], "tags": {"cycleway": "lane", "highway": "tertiary_link", "oneway": "yes"}}, {"type": "way", "id": 23699052, "nodes": [250601935, 7175406389], "tags": {"highway": "tertiary_link", "maxspeed": "50", "oneway": "yes", "surface": "asphalt"}}, {"type": "way", "id": 23699112, "nodes": [250166082, 1969685685], "tags": {"highway": "tertiary_link", "lanes": "2", "surface": "asphalt"}}, {"type": "way", "id": 23861311, "nodes": [258606849, 2591466995, 1706026017], "tags": {"highway": "tertiary_link", "oneway": "yes", "surface": "asphalt"}}, {"type": "way", "id": 24056418, "nodes": [705814617, 5103462305, 279898688], "tags": {"highway": "tertiary_link", "oneway": "yes", "surface": "asphalt"}}, {"type": "way", "id": 25029545, "nodes": [280467913, 4063645075, 4530261658, 1935345850], "tags": {"highway": "tertiary_link", "oneway": "yes"}}, {"type": "way", "id": 25730657, "nodes": [3114703871, 3114703881], "tags": {"highway": "tertiary_link"}}, {"type": "way", "id": 25767276, "nodes": [258075188, 2066632855, 2066632858, 281029428], "tags": {"cycleway:both": "no", "highway": "tertiary_link", "lane_markings": "no", "surface": "asphalt"}}, {"type": "way", "id": 26623582, "nodes": [632233861, 250601669], "tags": {"highway": "tertiary_link", "maxspeed": "50", "maxspeed:type": "FR:urban", "oneway": "yes", "surface": "asphalt"}}, {"type": "way", "id": 27652215, "nodes": [250224775, 282073664], "tags": {"highway": "tertiary_link"}}, {"type": "way", "id": 37566270, "nodes": [244645764, 1879234155, 4914607100, 4914607061, 1946032483, 249799832], "tags": {"highway": "tertiary_link", "lanes": "1", "oneway": "yes"}}, {"type": "way", "id": 39760325, "nodes": [476646639, 2503792345, 2503792341, 476645657], "tags": {"highway": "tertiary_link", "surface": "asphalt"}}, {"type": "way", "id": 42674628, "nodes": [533634094, 2072658552, 2072658558, 251538819], "tags": {"cycleway:left": "lane", "cycleway:left:lane": "advisory", "cycleway:right": "no", "highway": "tertiary_link", "lanes": "2", "oneway": "no", "surface": "asphalt"}}, {"type": "way", "id": 42674629, "nodes": [250371530, 2072658526, 2072658522, 533634092], "tags": {"highway": "tertiary_link"}}, {"type": "way", "id": 43576974, "nodes": [260950544, 4414453218, 2487877592], "tags": {"highway": "tertiary_link", "oneway": "yes", "surface": "asphalt"}}, {"type": "way", "id": 43938493, "nodes": [1909825189, 1983051444, 2072658466, 1909825185, 2072658463, 1909825181, 1923713407, 250287591], "tags": {"highway": "tertiary_link", "name": "Cours du Mar\u00e9chal Juin", "oneway": "yes", "surface": "asphalt"}}, {"type": "way", "id": 48064386, "nodes": [247889158, 6452092869, 6452092861, 6452092868, 247889069], "tags": {"cycleway": "lane", "highway": "tertiary_link", "lanes:backward": "2", "lanes:forward": "2", "lit": "yes", "maxspeed": "50", "source:maxspeed": "FR:urban", "surface": "asphalt", "turn:lanes:backward": "left|through", "turn:lanes:forward": "left|through"}}, {"type": "way", "id": 61158931, "nodes": [1970000856, 250181956], "tags": {"highway": "tertiary_link", "oneway": "yes", "surface": "asphalt"}}, {"type": "way", "id": 110279864, "nodes": [250207091, 255701980], "tags": {"highway": "tertiary_link", "surface": "asphalt"}}, {"type": "way", "id": 117617108, "nodes": [249810951, 1942801227, 6454879385, 1879102345, 1942801229, 249810952, 1942801232, 6454878282], "tags": {"highway": "tertiary_link", "oneway": "yes", "surface": "asphalt"}}, {"type": "way", "id": 174196569, "nodes": [250288068, 632233820], "tags": {"highway": "tertiary_link", "oneway": "yes", "surface": "asphalt"}}, {"type": "way", "id": 180274875, "nodes": [35232800, 1981045260, 5911304591, 35232801, 4907314596, 1981045238, 21459444, 35232776], "tags": {"highway": "tertiary_link", "lanes": "2", "oneway": "yes", "surface": "asphalt"}}, {"type": "way", "id": 182868037, "nodes": [1932291171, 1932291173, 4895226290, 1932291175, 1932291177, 4063645075, 4530261657, 1935345836], "tags": {"highway": "tertiary_link", "oneway": "yes", "surface": "asphalt"}}, {"type": "way", "id": 183268762, "nodes": [1973883953, 417092259, 261591344], "tags": {"highway": "tertiary_link", "surface": "asphalt"}}, {"type": "way", "id": 183268764, "nodes": [1936486452, 1936486454, 1936486466, 1936486464, 1973883953], "tags": {"highway": "tertiary_link", "lanes": "1", "oneway": "yes", "surface": "asphalt"}}, {"type": "way", "id": 183268765, "nodes": [1973883960, 1936486486, 1936486469, 1936486468, 1936486480, 261591344], "tags": {"highway": "tertiary_link", "oneway": "yes", "surface": "asphalt"}}, {"type": "way", "id": 184936948, "nodes": [1955022677, 1955022675, 1955022674, 1955022672, 1955022671, 3072882047], "tags": {"bicycle": "no", "highway": "tertiary_link", "lanes": "1", "oneway": "yes", "surface": "asphalt"}}, {"type": "way", "id": 185627041, "nodes": [250311318, 2000287034, 2000287035, 1962719187], "tags": {"cycleway:right": "no", "highway": "tertiary_link", "lane_markings": "no", "oneway": "yes", "surface": "asphalt"}}, {"type": "way", "id": 186304116, "nodes": [1969813994, 1969814013, 1969814015, 1969814017, 1969685531], "tags": {"highway": "tertiary_link", "oneway": "yes", "source": "cadastre-dgi-fr source : Direction G\u00e9n\u00e9rale des Imp\u00f4ts - Cadastre. Mise \u00e0 jour : 2012", "surface": "asphalt"}}, {"type": "way", "id": 186328360, "nodes": [1969987865, 1969987863, 1969987860, 1969987852, 1969987848, 244117784], "tags": {"highway": "tertiary_link", "oneway": "yes", "surface": "asphalt"}}, {"type": "way", "id": 186328362, "nodes": [1969987862, 1969987864, 1969987871, 1969987872, 1969987874, 1969987882], "tags": {"highway": "tertiary_link", "oneway": "yes", "surface": "asphalt"}}, {"type": "way", "id": 187035165, "nodes": [244117768, 280738634], "tags": {"cycleway:left": "lane", "highway": "tertiary_link", "lit": "yes", "maxspeed:type": "FR:urban", "surface": "asphalt"}}, {"type": "way", "id": 187403220, "nodes": [35232776, 2076358908, 2076358905, 279706833], "tags": {"cycleway:right": "no", "highway": "tertiary_link", "lane_markings": "no", "oneway": "yes", "surface": "asphalt"}}, {"type": "way", "id": 189403623, "nodes": [2000287054, 2000287051, 2000287049, 2000287047, 2000287046, 2000287044, 2000287041, 2000287036, 250311318], "tags": {"cycleway:right": "no", "highway": "tertiary_link", "lanes": "1", "oneway": "yes", "surface": "asphalt"}}, {"type": "way", "id": 189494752, "nodes": [2000178067, 2000178065, 2000178062, 2000178060, 2073096182, 259187477], "tags": {"highway": "tertiary_link", "lanes": "1", "name": "Rue Courpon", "oneway": "yes", "surface": "asphalt"}}, {"type": "way", "id": 191706936, "nodes": [250166198, 2022926567, 9053962608, 2022926576], "tags": {"highway": "tertiary_link", "name": "Place Gabriel Delaunay", "oneway": "yes"}}, {"type": "way", "id": 193449622, "nodes": [229911115, 281030228], "tags": {"highway": "tertiary_link", "oneway": "yes", "surface": "asphalt"}}, {"type": "way", "id": 194796312, "nodes": [3072882047, 5395132026, 2053010665, 2053010663], "tags": {"highway": "tertiary_link", "lane_markings": "no", "oneway": "yes", "surface": "asphalt"}}, {"type": "way", "id": 210564778, "nodes": [2206446336, 2586773607, 2206446321, 2587186537, 2587186539, 2206446278, 2587186541, 7069830997, 2206446261, 7069821676, 2206446256], "tags": {"highway": "tertiary_link", "lanes": "1", "maxspeed": "50", "oneway": "yes", "surface": "asphalt"}}, {"type": "way", "id": 210565221, "nodes": [2206446283, 7069821677, 2206451258, 2587186559, 2587186555, 2587186557, 2206451259, 4616284991, 2899175826, 4616285012, 2586773596, 2206451265], "tags": {"highway": "tertiary_link", "oneway": "yes"}}, {"type": "way", "id": 244561834, "nodes": [3140674006, 4414848193, 4414848192, 279121323], "tags": {"highway": "tertiary_link", "oneway": "yes", "sidewalk": "no", "surface": "asphalt"}}, {"type": "way", "id": 244561840, "nodes": [3140674015, 2518667373, 2518667371, 2518667369, 7179456582, 2518667367, 2518667368, 2518667370], "tags": {"highway": "tertiary_link", "name": "Avenue de la Vieille Tour", "oneway": "yes", "sidewalk": "separate", "surface": "asphalt"}}, {"type": "way", "id": 253175306, "nodes": [1706026011, 2591466992, 2591466993, 2591466994, 5520355192, 5520355191, 258606849], "tags": {"highway": "tertiary_link", "oneway": "yes", "surface": "asphalt"}}, {"type": "way", "id": 257004371, "nodes": [279815681, 260354794], "tags": {"highway": "tertiary_link", "oneway": "yes"}}, {"type": "way", "id": 257324939, "nodes": [280726298, 280726302], "tags": {"highway": "tertiary_link"}}, {"type": "way", "id": 257512007, "nodes": [279816876, 2496048875, 6572480351, 6572480352, 2496048873, 279815680, 2496048872, 279815681], "tags": {"highway": "tertiary_link", "oneway": "yes"}}, {"type": "way", "id": 288498299, "nodes": [2920560735, 4391584448, 2920560737, 2920560738, 2393739717], "tags": {"highway": "tertiary_link", "lanes": "1", "oneway": "yes", "surface": "asphalt"}}, {"type": "way", "id": 288498872, "nodes": [2920569201, 7024349740, 4391617365, 2920569203, 3736801965, 2920318031], "tags": {"highway": "tertiary_link", "maxspeed": "50", "oneway": "yes", "surface": "asphalt"}}, {"type": "way", "id": 288499146, "nodes": [2920570837, 2920570838, 2920570839, 2920570840, 2920476951], "tags": {"highway": "tertiary_link", "oneway": "yes", "surface": "asphalt"}}, {"type": "way", "id": 288499248, "nodes": [240713647, 7006990517, 2920572129, 2920572232, 4391584443, 2920572233, 2920572234, 2920505793], "tags": {"highway": "tertiary_link", "lanes": "1", "oneway": "yes", "surface": "asphalt"}}, {"type": "way", "id": 290652399, "nodes": [25214067, 6913967538], "tags": {"highway": "tertiary_link", "oneway": "yes", "oneway:bicycle": "no", "surface": "asphalt"}}, {"type": "way", "id": 311963900, "nodes": [282734521, 4132832753, 4132832754, 3177444136, 3177444135], "tags": {"cycleway:right": "no", "highway": "tertiary_link", "lanes": "1", "lit": "yes", "oneway": "yes"}}, {"type": "way", "id": 399739851, "nodes": [5538220084, 4088941768], "tags": {"highway": "tertiary_link", "lanes": "2", "oneway": "yes", "surface": "asphalt"}}, {"type": "way", "id": 405030662, "nodes": [280951023, 4088941767], "tags": {"highway": "tertiary_link", "oneway": "yes"}}, {"type": "way", "id": 441411190, "nodes": [2920476951, 2920318035], "tags": {"highway": "tertiary_link", "name": "Avenue Pey-Berland", "oneway": "yes", "surface": "asphalt"}}, {"type": "way", "id": 463932337, "nodes": [4088941767, 1879167941], "tags": {"highway": "tertiary_link", "oneway": "yes"}}, {"type": "way", "id": 579249542, "nodes": [279898688, 5103462310], "tags": {"cycleway": "opposite", "highway": "tertiary_link", "oneway": "yes", "oneway:bicycle": "no", "surface": "asphalt"}}, {"type": "way", "id": 595362379, "nodes": [4088941768, 4064981397], "tags": {"highway": "tertiary_link", "lanes": "2", "oneway": "yes", "surface": "asphalt"}}, {"type": "way", "id": 688169703, "nodes": [534588684, 1947667713, 1952403449, 1947667717, 247888815, 1947667728, 1952403457, 1947667742], "tags": {"cycleway:right": "separate", "highway": "tertiary_link", "lanes": "1", "oneway": "yes", "surface": "asphalt"}}, {"type": "way", "id": 688169704, "nodes": [1947667746, 6452201372, 247888881, 534588683, 247888882, 247888883, 1952403448, 534588682, 1952403443, 247888884, 1947667707, 1947667706, 1947667703, 247888382], "tags": {"cycleway:right": "separate", "highway": "tertiary_link", "lanes": "1", "lit": "yes", "maxspeed": "50", "oneway": "yes", "sidewalk": "separate", "surface": "asphalt"}}, {"type": "way", "id": 688359561, "nodes": [1942801246, 6454638652, 6454638656, 6454638653, 6454638654, 6454638655, 4914607060], "tags": {"highway": "tertiary_link", "lanes": "1", "oneway": "yes", "surface": "asphalt"}}, {"type": "way", "id": 688378067, "nodes": [4914607060, 6454638650], "tags": {"highway": "tertiary_link", "lanes": "1", "oneway": "yes", "surface": "asphalt"}}, {"type": "way", "id": 691278972, "nodes": [288948521, 6486480601], "tags": {"highway": "tertiary_link", "maxspeed": "30", "maxspeed:type": "sign", "surface": "asphalt"}}, {"type": "way", "id": 699901791, "nodes": [279816879, 279815688, 6572482872, 279816880, 290428894, 279816868, 279815651], "tags": {"highway": "tertiary_link", "oneway": "yes"}}, {"type": "way", "id": 768581183, "nodes": [250601935, 1968533244], "tags": {"highway": "tertiary_link", "oneway": "yes"}}, {"type": "way", "id": 769674460, "nodes": [643735936, 6917896360, 6917896358, 6917896367], "tags": {"highway": "tertiary_link"}}, {"type": "way", "id": 773721481, "nodes": [534588682, 247888817, 1952403444, 1952403445, 534588684], "tags": {"cycleway:right": "separate", "highway": "tertiary_link", "lanes": "1", "oneway": "yes", "surface": "asphalt"}}, {"type": "way", "id": 773721482, "nodes": [247888947, 1947667714, 247888818, 1952403446, 534588682], "tags": {"cycleway:right": "separate", "highway": "tertiary_link", "lanes": "1", "oneway": "yes", "surface": "asphalt"}}, {"type": "way", "id": 952510716, "nodes": [2920505793, 2393739717], "tags": {"highway": "tertiary_link", "lanes": "2", "surface": "asphalt"}}]}